Workbook

Sheet Backlog
A1: ID | B1: Etapa | C1: Fecha | D1: Día | E1: Clúster | F1: Rol | G1: Tipo | H1: Título propuesto (H1) | I1: Keyword objetivo | J1: Intención | K1: Audiencia | L1: Ángulo diferenciador | M1: Regla de redacción (sin verificación previa) | N1: Guía PDF (entregable Club 57) | O1: Origen | P1: Estado | Q1: Idea original del cliente | R1: Razón de valor (cliente)
A2: B01 | B2: Lanzamiento | C2: 46304 | D2: viernes | E2: Marca y Club 57 | F2: Pilar | G2: Pilar | H2: Truper, Pretul, Foset, Volteck y más: guía de marcas para elegir herramienta y material | I2: marcas truper | J2: Informacional / comercial | K2: B2C + B2B | L2: Hub de marca: conecta el catálogo (todo es familia Truper) con la decisión de compra. Pocos competidores locales explican las marcas con criterio de uso. | M2: Escribir solo con lo que muestra el catálogo del sitio (nombres de productos y categorías). No afirmar qué línea cubre cada marca ni garantías específicas; remitir a la etiqueta o ficha de cada producto. | N2: Guía de marcas Truper: cuál elegir según tu trabajo | O2: Propuesto por Claude (pendiente de aprobación del cliente) | P2: Backlog | Q2: — | R2: Pilar de marca: conecta el catálogo (todo es familia Truper) con la decisión de compra y alimenta los demás clústeres.
A3: B02 | B3: Lanzamiento | C3: 46304 | D3: viernes | E3: Herramientas y mantenimiento | F3: Pilar | G3: Pilar | H3: Kit básico de herramientas para el hogar: las 15 que sí necesitas (y cuáles dejar para después) | I3: herramientas básicas para el hogar | J3: Informacional / comercial | K3: B2C | L3: Pilar para principiantes con enfoque de presupuesto por niveles; sirve de hub hacia todos los artículos de herramientas. | M3: Conocimiento general estable. Sin precios; enlazar solo herramientas que existan en el catálogo. | N3: Checklist: caja de herramientas básica del hogar | O3: Propuesto por Claude (pendiente de aprobación del cliente) | P3: Backlog | Q3: — | R3: Pilar para principiantes: hub hacia todos los artículos de herramientas, con alta demanda de búsqueda general.
A4: B03 | B4: Lanzamiento | C4: 46304 | D4: viernes | E4: Construcción, fijación y materiales | F4: Pilar | G4: Pilar | H4: Cómo escoger el tamaño y tipo de broca correcto para cada material | I4: tipos de brocas | J4: Informacional | K4: B2C + B2B | L4: Tabla 'material → broca → taquete → tornillo' lista para el mostrador y para el cliente casero; evita roturas y reclamos. | M4: Conocimiento general estable. Diámetros y velocidades: remitir al empaque de la broca y al manual del taladro. | N4: Tabla rápida: broca, taquete y tornillo por material | O4: Cliente (idea #1) | P4: Backlog | Q4: Cómo escoger el tamaño y tipo de broca correcto para cada material | R4: B2C: Evita que el cliente dañe sus muros o rompa el material. B2B: Da argumentos técnicos al mostrador para hacer ventas cruzadas (taquete + broca + tornillo).
A5: B04 | B5: Lanzamiento | C5: 46304 | D5: viernes | E5: Plomería y agua | F5: Pilar | G5: Pilar | H5: PPR, PVC, CPVC o cobre: diferencias entre tuberías y cuál conviene en tu proyecto | I5: diferencia entre tubería ppr y pvc | J5: Informacional / comercial | K5: B2C + B2B | L5: Comparativa honesta con criterio de decisión por proyecto (casa nueva, remodelación, agua caliente) y con ángulo de agua dura local. | M5: Comparar por características generales (costo relativo, tipo de unión, uso). Sin límites numéricos de temperatura o presión: remitir a la ficha del fabricante. | N5: Comparador de tuberías: PPR, PVC, CPVC y cobre | O5: Cliente (idea #5) | P5: Backlog | Q5: Principales diferencias entre tuberías PPR, PVC, CPVC y Cobre | R5: B2C: Ayuda al usuario a tomar decisiones informadas de remodelación. B2B: Respalda al plomero/instalador al justificar cotizaciones de materiales ante sus clientes.
A6: B05 | B6: Lanzamiento | C6: 46304 | D6: viernes | E6: Electricidad e iluminación | F6: Pilar | G6: Pilar | H6: Calibre de cables eléctricos: cuál usar para cada electrodoméstico y cada circuito | I6: calibre de cable para casa | J6: Informacional / comercial | K6: B2C + B2B | L6: Pasa de la tabla fría a un cálculo guiado con ejemplos reales de aparatos del hogar; refuerza seguridad y normativa. | M6: Usar la regla práctica estándar 14/12/10 AWG ↔ 15/20/30 A, presentada como orientativa. Sin números de norma; indicar que un electricista valida la instalación. | N6: Tabla de calibres: qué cable para cada aparato | O6: Cliente (idea #8) | P6: Backlog | Q6: Guía de cables eléctricos: Qué calibre usar para cada electrodoméstico | R6: B2C: Previene cortocircuitos e incendios por sobrecarga. B2B: Facilita la venta de marcas especializadas (como Volteck o Truper) al explicar normativas de seguridad.
A7: B06 | B7: Lanzamiento | C7: 46304 | D7: viernes | E7: Pintura, sellado e impermeabilización | F7: Pilar | G7: Pilar | H7: Salitre y humedad en muros en Querétaro: cómo protegerlos y eliminarlos paso a paso | I7: salitre en paredes | J7: Informacional / comercial | K7: B2C + B2B | L7: Problema hiperlocal del Bajío con procedimiento claro, orden de productos y diagnóstico salitre vs moho. | M7: Procedimiento general. Tiempos de secado y dosificación: remitir a la etiqueta de cada producto. Sin fechas ni cifras de clima. | N7: Guía visual: salitre y humedad, diagnóstico y reparación | O7: Cliente (idea #6) | P7: Backlog | Q7: Cómo proteger tu casa en Querétaro del salitre y la humedad en muros | R7: B2C: Ataca un problema hiper-local y común en el Bajío (SEO local). B2B: Impulsa la venta de impermeabilizantes, selladores y aditivos para concreto.
A8: B07 | B8: Lanzamiento | C8: 46304 | D8: viernes | E8: Plomería y agua | F8: Pilar | G8: Pilar | H8: Tinaco o cisterna en Querétaro: qué considerar para instalarlo y no quedarte sin agua | I8: instalar tinaco | J8: Informacional / comercial | K8: B2C + B2B | L8: Guía local para escenarios de cortes de agua con calculadora simple y lista completa de componentes. | M8: Cálculo con un supuesto ilustrativo declarado como ejemplo (p. ej. consumo por persona), invitando al lector a ajustarlo. Hablar de cortes de agua en general, sin datos de colonias. | N8: Checklist de instalación de tinaco o cisterna | O8: Cliente (idea #12) | P8: Backlog | Q8: Qué considerar al instalar un tinaco o cisterna para evitar cortes de agua en Querétaro | R8: B2C: Guía de prevención ante tandeos locales (Alta búsqueda SEO). B2B: Tráfico segmentado por la necesidad de almacenamiento de agua, impulsando ticket alto.
A9: B08 | B9: Lanzamiento | C9: 46304 | D9: viernes | E9: Pintura, sellado e impermeabilización | F9: Pilar | G9: Pilar | H9: Brocha o rodillo: qué necesitas según la pintura (vinílica vs esmalte) | I9: brocha o rodillo | J9: Informacional | K9: B2C + B2B | L9: Decisión práctica por superficie y pintura para lograr un acabado profesional en casa; capacitación rápida para mostrador. | M9: Conocimiento general estable. No nombrar marcas de pintura ajenas al catálogo (IPESA incluida). Largos de felpa: remitir a la etiqueta. | N9: Guía rápida: qué herramienta usar según tu pintura | O9: Cliente (idea #2) | P9: Backlog | Q9: Qué tipo de brocha o rodillo necesito según la pintura (vinílica vs esmalte) | R9: B2C: Garantiza un acabado profesional en casa. B2B: Capacita al personal para recomendar la herramienta adecuada con pinturas de marcas reconocidas como IPESA.
A10: B09 | B10: Octubre 2026 | C10: 46308 | D10: martes | E10: Construcción, fijación y materiales | F10: Satélite | G10: Fondo | H10: Tipos de taquetes: cuál usar en tablaroca, concreto sólido o ladrillo hueco | I10: tipos de taquetes | J10: Informacional | K10: B2C + B2B | L10: Diagnóstico del muro antes de elegir y trío broca–taquete–tornillo explicado; enfoque en evitar accidentes. | M10: Conocimiento general. Sin cifras de carga: remitir al empaque del taquete. | N10: Guía de taquetes por tipo de muro | O10: Cliente (idea #7) | P10: Backlog | Q10: Tipos de taquetes: Cuál usar en tablaroca, concreto sólido o ladrillo hueco | R10: B2C: Previene accidentes (ej. repisas o pantallas caídas). B2B: Reduce los reclamos en mostrador por 'productos que no sirven' por mala instalación.
A11: B10 | B11: Octubre 2026 | C11: 46310 | D11: jueves | E11: Marca y Club 57 | F11: Conversión (Club 57) | G11: Corto | H11: Club 57: cómo funciona, cómo ganar puntos y qué recibes al registrarte | I11: club 57 ferretería 57 | J11: Informacional / comercial | K11: B2C | L11: Artículo de conversión: conecta el blog con el registro a Club 57, donde se entregan las guías PDF. | M11: Leer los valores vigentes de Club 57 desde la configuración del admin al redactar; no hardcodear cifras ni mencionar proveedores técnicos. | N11: Guía de bienvenida a Club 57 | O11: Propuesto por Claude (pendiente de aprobación del cliente) | P11: Backlog | Q11: — | R11: Conversión: explica el programa donde se entregan las guías PDF y las promociones para miembros.
A12: B11 | B12: Octubre 2026 | C12: 46312 | D12: sábado | E12: Plomería y agua | F12: Satélite | G12: Fin de semana | H12: Cómo destapar la tubería del lavabo de forma segura sin dañar el PVC | I12: cómo destapar un lavabo | J12: Informacional | K12: B2C + B2B | L12: Procedimiento seguro priorizando métodos mecánicos y cuidado del PVC. | M12: Conocimiento general. Seguir la etiqueta de cada destapacaños; sin temperaturas exactas. | N12: Guía de emergencia: lavabo tapado | O12: Cliente (idea #13) | P12: Backlog | Q12: Cómo destapar una tubería del lavabo de forma segura sin dañar el PVC | R12: B2C: Soluciona un problema de emergencia en casa. B2B: Posiciona la venta de químicos destapacaños, chupones y guías mecánicas.
A13: B12 | B13: Octubre 2026 | C13: 46315 | D13: martes | E13: Seguridad y protección | F13: Pilar | G13: Fondo | H13: Cómo elegir un candado anticizalla para exteriores y cortinas de negocio | I13: candado anticizalla | J13: Informacional / comercial | K13: B2C + B2B | L13: Criterios de compra claros + mini auditoría de seguridad lista para imprimir, útil para dueños de negocio. | M13: Criterios generales de compra. No prometer «inviolable» ni citar estadísticas; sin grados de seguridad específicos. | N13: Auditoría de seguridad básica para casa o negocio | O13: Cliente (idea #9) | P13: Backlog | Q13: Cómo elegir un buen candado anticizalla para exteriores y cortinas de negocios | R13: B2C/B2B: Aborda la preocupación de seguridad de locales y hogares, ideal para respaldar un PDF sobre 'Auditoría de seguridad básica'.
... A57: B56 | B57: Enero 2027 | C57: 46417 | D57: sábado | E57: Herramientas y mantenimiento | F57: Satélite | G57: Fin de semana | H57: Guía rápida de lijas: qué número de grano usar para madera, metal o agua | I57: tipos de lijas | J57: Informacional | K57: B2C + B2B | L57: Secuencia de granos por proyecto en una tabla simple. | M57: Conocimiento general. Granos habituales, sin ser prescriptivos. | N57: Tabla de lijas: granos y secuencias | O57: Cliente (idea #32) | P57: Backlog | Q57: Guía rápida de lijas: Qué número de grano usar para madera, metal o agua | R57: B2C: Asegura acabados perfectos. B2B: Evita errores del mostrador al surtir listas de materiales para carpinteros y pintores de autos.
A58: B57 | B58: Reserva | E58: Herramientas y mantenimiento | F58: Satélite | G58: Reserva | H58: Catálogo de herramientas manuales para preparar tu jardín o patio en primavera | I58: herramientas de jardinería | J58: Informacional / estacional | K58: B2C | L58: Lista estacional por tarea. | M58: Conocimiento general. Sin recomendaciones agronómicas específicas. | N58: Calendario de jardín: primavera | O58: Cliente (idea #55) | P58: Backlog | Q58: Catálogo de herramientas manuales para preparar tu jardín o patio en primavera | R58: B2C: Contenido estacional para rotar inventario de tijeras de podar, mangueras, palas, aspersores y fertilizantes.
A59: B58 | B59: Reserva | E59: Pintura, sellado e impermeabilización | F59: Satélite | G59: Reserva | H59: Impermeabilizantes acrílicos vs prefabricados (manto): cuál conviene más | I59: impermeabilizante acrílico vs manto | J59: Informacional / comercial | K59: B2C + B2B | L59: Comparativa por inversión a largo plazo; atrae a contratistas e instaladores. | M59: Conocimiento general. Duración: remitir a la garantía del fabricante. | N59: Guía de impermeabilización de azotea | O59: Cliente (idea #21) | P59: Backlog | Q59: Impermeabilizantes acrílicos vs prefabricados (manto): Cuál conviene más | R59: B2C: Educa sobre la inversión a largo plazo en mantenimiento. B2B: Atrae a contratistas e instaladores que buscan proveeduría estable.

Sheet Briefs SEO
A1: ID | B1: Fecha | C1: Slug | D1: URL canónica | E1: Title tag (≤60) | F1: Car. | G1: Meta description (120–155) | H1: Car. | I1: H1 | J1: Keyword principal | K1: Keywords secundarias / long-tail | L1: Preguntas frecuentes (sección FAQ) | M1: Estructura (H2) | N1: Puntos clave y reglas de contenido | O1: Extensión (palabras) | P1: Schema.org | Q1: Productos / categorías a enlazar | R1: Enlaces internos (ya publicados): enlazar a estos y agregar enlace de vuelta desde cada uno | S1: Enlaces futuros (se agregan cuando se publique el destino) | T1: Pilar del clúster | U1: Regla de redacción (sin verificación previa) | V1: Enfoque local Querétaro | W1: CTA hacia Club 57 (guía PDF) | X1: Estado brief
A2: B01 | B2: 46304 | C2: marcas-truper-pretul-foset-volteck-guia | D2: ="https://ferreteria57.com/blog/"&C2 -> https://ferreteria57.com/blog/marcas-truper-pretul-foset-volteck-guia | E2: Marcas Truper: Pretul, Foset, Volteck y cuál elegir | F2: =LEN(E2) -> 51 | G2: Qué es cada marca de la familia Truper (Pretul, Foset, Volteck, Fiero, Hermex y Klintek), para qué sirve y cómo elegir según tu trabajo y presupuesto. | H2: =LEN(G2) -> 150 | I2: Truper, Pretul, Foset, Volteck y más: guía de marcas para elegir herramienta y material | J2: marcas truper | K2: pretul vs truper; qué es pretul; volteck material eléctrico; foset herramientas; hermex; fiero; klintek | L2: • ¿Qué diferencia hay entre Truper y Pretul? • ¿Qué marcas pertenecen a Truper? • ¿Qué marca conviene para uso doméstico y cuál para uso diario de taller? | M2: 1. La familia de marcas que vendemos en Ferretería 57 2. Truper: la marca principal y qué ofrece 3. Una por una: Pretul, Foset, Volteck, Fiero, Hermex y Klintek (qué línea cubre y para quién) 4. Truper vs Pretul: cuándo conviene pagar más y cuándo no (frecuencia de uso, exigencia, presupuesto) 5. Tabla: tu tarea → la marca o línea que conviene 6. Cómo encontrar cada marca en nuestro catálogo 7. Preguntas frecuentes | N2: • Tono honesto: no denigrar ninguna marca; el criterio es uso (ocasional vs diario), exigencia del trabajo y presupuesto • Tabla comparativa solo con texto (sin imágenes), una fila por marca: línea de producto, usuario típico, ejemplo de producto del catálogo • Describir cada marca solo con lo que muestra el catálogo del sitio; no afirmar líneas ni garantías que no estén ahí • Pieza ancla de marca: enlaza a todos los clústeres | O2: 2.000–2.500 | P2: BlogPosting + BreadcrumbList + FAQPage | Q2: Catálogo completo por marca (filtro/ página de marca si existe); ejemplos de 1 producto por marca con enlace a su ficha | R2: B02 · Herramientas básicas para el hogar: las 15 esenciales → ancla: «herramientas básicas para el hogar» B03 · Cómo escoger la broca correcta según el material → ancla: «tipos de brocas» B05 · Calibre de cable eléctrico para cada electrodoméstico → ancla: «calibre de cable para casa» B08 · Brocha o rodillo: cuál usar con pintura vinílica o esmalte → ancla: «brocha o rodillo» | S2: B10 · Club 57 de Ferretería 57: cómo ganar puntos y beneficios → ancla: «club 57 ferretería 57» B33 · Merchandising para ferreterías: exhibe y vende más → ancla: «merchandising para ferreterías» B40 · 5 ventajas de comprar en una ferretería de barrio → ancla: «ferretería en querétaro» | T2: (es el pilar) | U2: Escribir solo con lo que muestra el catálogo del sitio (nombres de productos y categorías). No afirmar qué línea cubre cada marca ni garantías específicas; remitir a la etiqueta o ficha de cada producto. | V2: Mencionar que se puede ver y comprar en tienda (Lateral Carretera Federal 57 No. 230, Casa Blanca) y en línea con envío local. | W2: Descarga gratis la guía «Guía de marcas Truper: cuál elegir según tu trabajo» al registrarte en Club 57. | X2: Brief listo
A3: B02 | B3: 46304 | C3: kit-basico-herramientas-hogar | D3: ="https://ferreteria57.com/blog/"&C3 -> https://ferreteria57.com/blog/kit-basico-herramientas-hogar | E3: Herramientas básicas para el hogar: las 15 esenciales | F3: =LEN(E3) -> 53 | G3: Arma tu caja de herramientas sin gastar de más: 15 herramientas básicas para el hogar, en tres niveles de inversión, con consejos para elegir cada una. | H3: =LEN(G3) -> 151 | I3: Kit básico de herramientas para el hogar: las 15 que sí necesitas (y cuáles dejar para después) | J3: herramientas básicas para el hogar | K3: caja de herramientas básica; qué herramientas necesito en casa; kit de herramientas para principiantes; herramientas esenciales | L3: • ¿Qué herramientas básicas debe tener una casa? • ¿Cuánto cuesta armar una caja de herramientas básica? • ¿Qué herramienta eléctrica conviene comprar primero? | M3: 1. Antes de comprar: qué vas a reparar realmente 2. Nivel 1 – lo indispensable (martillo, desarmadores, pinzas, flexómetro, nivel, cutter, llave ajustable…) 3. Nivel 2 – cuando ya haces más cosas (juego de llaves, serrucho/segueta, pistola de silicón, taladro) 4. Nivel 3 – para proyectos (rotomartillo, caladora, multímetro) 5. Cómo elegir calidad sin pagar de más 6. Cómo guardar y ordenar tu caja 7. Preguntas frecuentes | N3: • 15 herramientas distribuidas en 3 niveles; cada una con: para qué sirve, qué buscar al comprarla, error común • Incluir el vínculo hacia cada artículo detallado (brocas, pinzas, flexómetros, multímetro) • Sin precios fijos en el texto: remitir al catálogo (los precios cambian) • Pieza pilar del clúster Herramientas | O3: 2.000–2.500 | P3: BlogPosting + BreadcrumbList + FAQPage | Q3: Martillos, desarmadores, pinzas, flexómetros, niveles, cutter, llaves ajustables, taladros (según catálogo) | R3: B01 · Marcas Truper: Pretul, Foset, Volteck y cuál elegir → ancla: «marcas truper» B03 · Cómo escoger la broca correcta según el material → ancla: «tipos de brocas» | S3: B09 · Tipos de taquetes: cuál usar en tablaroca y concreto → ancla: «tipos de taquetes» B10 · Club 57 de Ferretería 57: cómo ganar puntos y beneficios → ancla: «club 57 ferretería 57» B20 · Cómo instalar un soporte de TV en la pared, nivelado → ancla: «cómo instalar soporte de tv» B25 · Tipos de pinzas: de presión, electricista, punta y corte → ancla: «tipos de pinzas» B26 · Cómo quitar el óxido de herramientas y metales → ancla: «cómo quitar el óxido» B28 · Tipos de pegamentos: contacto, epóxico y cianoacrilato → ancla: «tipos de pegamentos» B29 · Cómo cambiar el sapo y herrajes del tanque del escusado → ancla: «cambiar sapo del tanque del escusado» B35 · Herramientas para la cajuela del auto en emergencias → ancla: «kit de emergencia para auto» B44 · Cómo organizar el tablero de herramientas del garaje → ancla: «organizar herramientas» B46 · Llaves y dados: medida milimétrica vs pulgadas → ancla: «llaves milimétricas vs estándar» B50 · Cómo usar un multímetro: contactos, pilas y fusibles → ancla: «cómo usar un multímetro» B51 · Discos de corte: diamante, abrasivo y para madera → ancla: «tipos de discos de corte» B53 · Mantenimiento de herramientas eléctricas: más vida útil → ancla: «mantenimiento de herramientas eléctricas» B55 · Cómo leer un flexómetro: pulgadas, fracciones y mm → ancla: «cómo leer un flexómetro» B56 · Guía de lijas: qué grano usar en madera, metal y agua → ancla: «tipos de lijas» B57 · Herramientas para preparar tu jardín en primavera → ancla: «herramientas de jardinería» | T3: (es el pilar) | U3: Conocimiento general estable. Sin precios; enlazar solo herramientas que existan en el catálogo. | V3: Mencionar asesoría presencial en el mostrador para armar el kit. | W3: Descarga gratis la guía «Checklist: caja de herramientas básica del hogar» al registrarte en Club 57. | X3: Brief listo
A4: B03 | B4: 46304 | C4: como-escoger-broca-correcta-para-cada-material | D4: ="https://ferreteria57.com/blog/"&C4 -> https://ferreteria57.com/blog/como-escoger-broca-correcta-para-cada-material | E4: Cómo escoger la broca correcta según el material | F4: =LEN(E4) -> 48 | G4: Aprende qué broca usar en concreto, madera, metal, tablaroca o azulejo, cómo elegir el diámetro y evita dañar tus muros o romper el material. | H4: =LEN(G4) -> 141 | I4: Cómo escoger el tamaño y tipo de broca correcto para cada material | J4: tipos de brocas | K4: qué broca usar para concreto; broca para pared; brocas para metal; brocas para madera; broca para azulejo; tamaño de broca para taquete | L4: • ¿Qué broca se usa para perforar concreto? • ¿Cómo sé qué diámetro de broca necesito para un taquete? • ¿Se puede usar la misma broca para madera y para metal? | M4: 1. Por qué importa elegir la broca correcta (qué se daña si te equivocas) 2. Brocas por material: concreto y mampostería, madera, metal, vidrio/azulejo, tablaroca 3. Partes de una broca: vástago, punta, estrías, recubrimientos 4. Cómo elegir el diámetro (relación broca–taquete–tornillo) y la profundidad 5. Taladro, taladro percutor o rotomartillo: cuál va con cada broca 6. Errores comunes (velocidad, presión, no marcar, no limpiar el polvo) 7. Preguntas frecuentes | N4: • Concreto/mampostería: punta de carburo de tungsteno y uso con percusión; azulejo y porcelanato: broca específica y sin percusión • Metal: acero rápido (HSS); madera: brocas de punta, de pala, sierra copa • Regla práctica: broca del mismo diámetro que el taquete y un poco más profunda que su longitud • Tabla de tres columnas: material / broca / consejo de uso. Evitar tecnicismos sin explicar • Venta cruzada natural: broca + taquete + tornillo (explicitar el trío) | O4: 2.000–2.500 | P4: BlogPosting + BreadcrumbList + FAQPage | Q4: Brocas para concreto, metal y madera; sierras copa; taquetes; tornillería; taladros y rotomartillos | R4: B01 · Marcas Truper: Pretul, Foset, Volteck y cuál elegir → ancla: «marcas truper» B02 · Herramientas básicas para el hogar: las 15 esenciales → ancla: «herramientas básicas para el hogar» | S4: B09 · Tipos de taquetes: cuál usar en tablaroca y concreto → ancla: «tipos de taquetes» B20 · Cómo instalar un soporte de TV en la pared, nivelado → ancla: «cómo instalar soporte de tv» B28 · Tipos de pegamentos: contacto, epóxico y cianoacrilato → ancla: «tipos de pegamentos» B33 · Merchandising para ferreterías: exhibe y vende más → ancla: «merchandising para ferreterías» B37 · Remachadora manual y medida de remaches: cómo elegir → ancla: «remachadora manual» B42 · Tornillería de acero inoxidable: grados y cuándo usarla → ancla: «tornillería de acero inoxidable» B44 · Cómo organizar el tablero de herramientas del garaje → ancla: «organizar herramientas» B47 · Herramientas para tablaroca: tu primer muro falso → ancla: «herramientas para tablaroca» B48 · Soldadura 6013 vs 7018: diferencias y cuándo usarlas → ancla: «soldadura 6013 y 7018» B53 · Mantenimiento de herramientas eléctricas: más vida útil → ancla: «mantenimiento de herramientas eléctricas» B54 · Cemento blanco, gris, mortero y yeso: diferencias → ancla: «diferencia entre cemento y mortero» B56 · Guía de lijas: qué grano usar en madera, metal y agua → ancla: «tipos de lijas» | T4: (es el pilar) | U4: Conocimiento general estable. Diámetros y velocidades: remitir al empaque de la broca y al manual del taladro. | V4: Muros de concreto y tabique de la zona (Bajío): mencionar que el tabique hueco y el block piden otro tratamiento (ver artículo de taquetes). | W4: Descarga gratis la guía «Tabla rápida: broca, taquete y tornillo por material» al registrarte en Club 57. | X4: Brief listo
A5: B04 | B5: 46304 | C5: diferencias-tuberia-ppr-pvc-cpvc-cobre | D5: ="https://ferreteria57.com/blog/"&C5 -> https://ferreteria57.com/blog/diferencias-tuberia-ppr-pvc-cpvc-cobre | E5: Tubería PPR, PVC, CPVC o cobre: diferencias y cuál usar | F5: =LEN(E5) -> 55 | G5: Compara las tuberías PPR, PVC, CPVC y cobre: costo, resistencia, temperatura, instalación y en qué casos conviene cada una en tu casa u obra. | H5: =LEN(G5) -> 141 | I5: PPR, PVC, CPVC o cobre: diferencias entre tuberías y cuál conviene en tu proyecto | J5: diferencia entre tubería ppr y pvc | K5: tubería ppr vs cobre; cpvc para agua caliente; qué tubería usar para agua potable; tubería para agua caliente; ppr ventajas | L5: • ¿Cuál es mejor, tubería PPR o cobre? • ¿Qué tubería se usa para agua caliente en casa? • ¿Se puede unir tubería PVC con CPVC o con PPR? | M5: 1. Cuatro materiales, cuatro formas de unir (cementado, termofusión, soldadura) 2. PVC hidráulico: agua fría y usos 3. CPVC: agua caliente y fría 4. PPR: termofusión, durabilidad y herramienta necesaria 5. Cobre: ventajas, costo y mantenimiento 6. Tabla comparativa: costo, temperatura, instalación, vida útil, herramienta 7. Qué conviene en una casa de Querétaro (agua dura y sarro) 8. Preguntas frecuentes | N5: • Cuidar rigor: límites de temperatura y presión solo con ficha técnica del fabricante • Aclarar que PVC sanitario/drenaje es otro producto (ver artículo de cédulas) • Mencionar herramientas y consumibles: termofusora, cortatubos, cemento solvente, soldadura, cinta • Tabla comparativa solo en texto; sin imágenes | O5: 2.000–2.500 | P5: BlogPosting + BreadcrumbList + FAQPage | Q5: Tubería y conexiones PPR, PVC, CPVC y cobre; termofusoras; cortatubos; cementos; cinta teflón (ver catálogo) | R5: B07 · Tinaco o cisterna en Querétaro: guía de instalación → ancla: «instalar tinaco» | S5: B10 · Club 57 de Ferretería 57: cómo ganar puntos y beneficios → ancla: «club 57 ferretería 57» B11 · Cómo destapar el lavabo sin dañar la tubería de PVC → ancla: «cómo destapar un lavabo» B13 · Cinta teflón: para qué sirve y cómo se aplica bien → ancla: «cinta teflón» B14 · Mantenimiento del calentador solar antes del frío → ancla: «mantenimiento calentador solar» B17 · Cómo purgar un boiler para quitarle el sarro paso a paso → ancla: «purgar boiler» B18 · Bomba de agua: periférica o centrífuga, cómo elegir → ancla: «bomba de agua para casa» B19 · 10 herramientas para iniciar tu negocio de plomería → ancla: «herramientas de plomero» B23 · Por qué baja la presión del agua en la regadera → ancla: «poca presión de agua en la regadera» B28 · Tipos de pegamentos: contacto, epóxico y cianoacrilato → ancla: «tipos de pegamentos» B29 · Cómo cambiar el sapo y herrajes del tanque del escusado → ancla: «cambiar sapo del tanque del escusado» B32 · Cómo reparar una fuga en la llave mezcladora → ancla: «reparar llave mezcladora» B39 · Tubos de PVC: qué significan cédula 40, 80 y sanitario → ancla: «cédula 40 y 80 pvc» | T5: (es el pilar) | U5: Comparar por características generales (costo relativo, tipo de unión, uso). Sin límites numéricos de temperatura o presión: remitir a la ficha del fabricante. | V5: Contexto local cualitativo del Bajío (clima, agua, comercio) sin cifras, estadísticas ni fechas. | W5: Descarga gratis la guía «Comparador de tuberías: PPR, PVC, CPVC y cobre» al registrarte en Club 57. | X5: Brief listo
A6: B05 | B6: 46304 | C6: calibre-de-cable-electrico-para-cada-electrodomestico | D6: ="https://ferreteria57.com/blog/"&C6 -> https://ferreteria57.com/blog/calibre-de-cable-electrico-para-cada-electrodomestico | E6: Calibre de cable eléctrico para cada electrodoméstico | F6: =LEN(E6) -> 53 | G6: Qué calibre de cable necesitas para contactos, iluminación, minisplit, refrigerador y más. Cómo calcular por amperes y evita sobrecargas. | H6: =LEN(G6) -> 137 | I6: Calibre de cables eléctricos: cuál usar para cada electrodoméstico y cada circuito | J6: calibre de cable para casa | K6: qué calibre de cable usar; cable calibre 12 o 14; calibre de cable para minisplit; tabla de calibres de cable awg; cable thw | L6: • ¿Qué calibre de cable se usa para los contactos de una casa? • ¿Qué pasa si uso un cable de menor calibre del necesario? • ¿Cómo calculo el calibre según los watts de un aparato? | M6: 1. Por qué el calibre importa (calor, caídas de voltaje, riesgo de incendio) 2. Cómo leer el calibre: AWG, sección y capacidad en amperes 3. Fórmula fácil: watts ÷ volts = amperes (ejemplo resuelto) 4. Tabla orientativa por uso: iluminación, contactos, minisplit, boiler, lavadora, estufa eléctrica 5. Tipos de cable (THW, THHW-LS, flexible) y colores 6. Cuándo llamar a un electricista 7. Preguntas frecuentes | N6: • Contenido de seguridad: aviso al inicio de que la tabla es orientativa y que la instalación la valida un electricista; sin citar números de norma • Regla práctica estándar: 14 AWG para 15 A, 12 AWG para 20 A y 10 AWG para 30 A; ejemplo numérico con 127 V y margen de seguridad en cargas continuas • Evitar recomendar modificar el centro de carga sin electricista • Venta ligada a Volteck/Truper solo si el catálogo lo respalda | O6: 2.000–2.500 | P6: BlogPosting + BreadcrumbList + FAQPage | Q6: Cable THW/THHW, cable flexible, interruptores termomagnéticos, centros de carga, conectores (ver catálogo) | R6: B01 · Marcas Truper: Pretul, Foset, Volteck y cuál elegir → ancla: «marcas truper» | S6: B10 · Club 57 de Ferretería 57: cómo ganar puntos y beneficios → ancla: «club 57 ferretería 57» B15 · Diablitos y falsos contactos: riesgos de tu instalación → ancla: «diablito eléctrico peligro» B16 · Conectores eléctricos: capuchones, regletas y cinta → ancla: «conectores eléctricos» B21 · Focos LED vs ahorradores: lúmenes, watts y color → ancla: «focos led vs ahorradores» B38 · Cómo cambiar una pastilla termomagnética con seguridad → ancla: «pastilla termomagnética» B50 · Cómo usar un multímetro: contactos, pilas y fusibles → ancla: «cómo usar un multímetro» | T6: (es el pilar) | U6: Usar la regla práctica estándar 14/12/10 AWG ↔ 15/20/30 A, presentada como orientativa. Sin números de norma; indicar que un electricista valida la instalación. | V6: Contexto local cualitativo del Bajío (clima, agua, comercio) sin cifras, estadísticas ni fechas. | W6: Descarga gratis la guía «Tabla de calibres: qué cable para cada aparato» al registrarte en Club 57. | X6: Brief listo
A7: B06 | B7: 46304 | C7: salitre-y-humedad-en-muros-queretaro | D7: ="https://ferreteria57.com/blog/"&C7 -> https://ferreteria57.com/blog/salitre-y-humedad-en-muros-queretaro | E7: Salitre y humedad en muros en Querétaro: cómo evitarlos | F7: =LEN(E7) -> 55 | G7: Por qué sale salitre en tus muros, cómo eliminarlo y qué productos usar para proteger tu casa de la humedad en Querétaro. Guía paso a paso. | H7: =LEN(G7) -> 139 | I7: Salitre y humedad en muros en Querétaro: cómo protegerlos y eliminarlos paso a paso | J7: salitre en paredes | K7: cómo quitar el salitre de las paredes; humedad en muros qué hacer; impermeabilizar muros interiores; anti salitre; pintura para salitre; humedad por capilaridad | L7: • ¿Qué causa el salitre en las paredes? • ¿Cómo se quita el salitre y se evita que regrese? • ¿Qué pintura o sellador sirve para muros con humedad? | M7: 1. Qué es el salitre y por qué aparece (sales + humedad) 2. Primero encuentra el origen: fuga, capilaridad, lluvia o condensación 3. Paso a paso para eliminarlo: raspar, cepillar, limpiar y dejar secar 4. Productos según el caso: sellador/fijador, impermeabilizante para muros, pintura apropiada, aditivos para mortero 5. Prevención: impermeabilizar azotea, bajadas, juntas, jardineras y drenaje 6. Salitre vs moho: cómo distinguirlos 7. Preguntas frecuentes | N7: • Pasos ordenados con materiales y orden de aplicación (no pintar sobre muro húmedo) • Advertencia: no mezclar productos de limpieza; usar guantes y protección respiratoria • Si hay fuga o humedad estructural, derivar a especialista • Venta cruzada: cepillo de alambre, espátula, sellador, impermeabilizante, pintura, guantes y mascarilla | O7: 2.000–2.500 | P7: BlogPosting + BreadcrumbList + FAQPage | Q7: Cepillos de alambre, espátulas, selladores, impermeabilizantes, aditivos para concreto, pintura, guantes y protección respiratoria | R7: B08 · Brocha o rodillo: cuál usar con pintura vinílica o esmalte → ancla: «brocha o rodillo» | S7: B24 · Cómo calcular cuánta pintura o impermeabilizante necesitas → ancla: «cómo calcular pintura» B30 · Silicón, sellador acrílico y poliuretano: diferencias → ancla: «diferencia entre silicón y sellador acrílico» B41 · Cómo limpiar y guardar brochas y rodillos para que duren → ancla: «cómo limpiar brochas» B43 · Silicón automotriz vs sellador de construcción → ancla: «silicón de alta temperatura» B45 · EPP en la obra: guía del equipo de protección personal → ancla: «equipo de protección personal en obra» B54 · Cemento blanco, gris, mortero y yeso: diferencias → ancla: «diferencia entre cemento y mortero» B58 · Impermeabilizante acrílico vs manto: cuál conviene → ancla: «impermeabilizante acrílico vs manto» | T7: B08 | U7: Procedimiento general. Tiempos de secado y dosificación: remitir a la etiqueta de cada producto. Sin fechas ni cifras de clima. | V7: Contexto local cualitativo del Bajío (clima, agua, comercio) sin cifras, estadísticas ni fechas. | W7: Descarga gratis la guía «Guía visual: salitre y humedad, diagnóstico y reparación» al registrarte en Club 57. | X7: Brief listo
A8: B07 | B8: 46304 | C8: instalar-tinaco-o-cisterna-queretaro | D8: ="https://ferreteria57.com/blog/"&C8 -> https://ferreteria57.com/blog/instalar-tinaco-o-cisterna-queretaro | E8: Tinaco o cisterna en Querétaro: guía de instalación | F8: =LEN(E8) -> 51 | G8: Qué considerar para instalar un tinaco o cisterna en Querétaro: capacidad, ubicación, bomba y accesorios para no quedarte sin agua en los cortes. | H8: =LEN(G8) -> 145 | I8: Tinaco o cisterna en Querétaro: qué considerar para instalarlo y no quedarte sin agua | J8: instalar tinaco | K8: cisterna o tinaco cuál conviene; capacidad de tinaco por persona; tinaco y bomba; altura del tinaco para buena presión; cortes de agua querétaro; tandeos de agua | L8: • ¿Qué capacidad de tinaco o cisterna necesito para mi familia? • ¿A qué altura debo instalar el tinaco para tener buena presión? • ¿Cada cuánto se debe lavar un tinaco o cisterna? | M8: 1. Tinaco, cisterna o ambos: cómo decidir 2. Cómo calcular la capacidad según el número de personas 3. Dónde instalarlo: base, nivel, altura y acceso 4. Accesorios que no pueden faltar: flotador, válvulas, filtro, conexiones, bomba 5. Mantenimiento y limpieza periódica 6. Checklist de instalación 7. Preguntas frecuentes | N8: • Cálculo con ejemplo resuelto (consumo por persona/día) • Explicar relación altura–presión en lenguaje simple (sin fórmulas pesadas) • Enlazar a bomba de agua y tuberías para completar la compra • Ticket alto: dejar claro el conjunto de componentes | O8: 2.000–2.500 | P8: BlogPosting + BreadcrumbList + FAQPage | Q8: Tinacos, cisternas, flotadores, válvulas, bombas presurizadoras, conexiones y tubería | R8: B04 · Tubería PPR, PVC, CPVC o cobre: diferencias y cuál usar → ancla: «diferencia entre tubería ppr y pvc» | S8: B13 · Cinta teflón: para qué sirve y cómo se aplica bien → ancla: «cinta teflón» B18 · Bomba de agua: periférica o centrífuga, cómo elegir → ancla: «bomba de agua para casa» B23 · Por qué baja la presión del agua en la regadera → ancla: «poca presión de agua en la regadera» | T8: B04 | U8: Cálculo con un supuesto ilustrativo declarado como ejemplo (p. ej. consumo por persona), invitando al lector a ajustarlo. Hablar de cortes de agua en general, sin datos de colonias. | V8: Contexto local cualitativo del Bajío (clima, agua, comercio) sin cifras, estadísticas ni fechas. | W8: Descarga gratis la guía «Checklist de instalación de tinaco o cisterna» al registrarte en Club 57. | X8: Brief listo
A9: B08 | B9: 46304 | C9: brocha-o-rodillo-segun-pintura-vinilica-esmalte | D9: ="https://ferreteria57.com/blog/"&C9 -> https://ferreteria57.com/blog/brocha-o-rodillo-segun-pintura-vinilica-esmalte | E9: Brocha o rodillo: cuál usar con pintura vinílica o esmalte | F9: =LEN(E9) -> 58 | G9: Elige la brocha o rodillo correcto según uses pintura vinílica o esmalte, el tipo de superficie y el acabado que buscas. Guía práctica. | H9: =LEN(G9) -> 135 | I9: Brocha o rodillo: qué necesitas según la pintura (vinílica vs esmalte) | J9: brocha o rodillo | K9: qué rodillo usar para pintar paredes; brocha para esmalte; diferencia pintura vinílica y esmalte; rodillo de felpa o espuma; cómo pintar una pared | L9: • ¿Qué rodillo se usa para pintura vinílica? • ¿Qué brocha es mejor para esmalte? • ¿Cuál es la diferencia entre pintura vinílica y esmalte? | M9: 1. Vinílica vs esmalte: qué es cada una y dónde se usa 2. Rodillos: felpa corta, media y larga; espuma 3. Brochas: cerdas naturales vs sintéticas y anchos 4. Tabla: superficie + pintura → herramienta recomendada 5. Accesorios que completan el trabajo (charola, extensión, cinta de enmascarar) 6. Errores que arruinan el acabado 7. Preguntas frecuentes | N9: • Tabla de decisión de 3 columnas: superficie / pintura / herramienta • Aclarar base agua vs base solvente y ventilación • No nombrar marcas de pintura ajenas al catálogo (IPESA incluida) • Enlazar a cálculo de pintura y limpieza de brochas | O9: 2.000–2.500 | P9: BlogPosting + BreadcrumbList + FAQPage | Q9: Brochas, rodillos, charolas, extensiones, cinta de enmascarar, espátulas, pinturas (según catálogo) | R9: B01 · Marcas Truper: Pretul, Foset, Volteck y cuál elegir → ancla: «marcas truper» B06 · Salitre y humedad en muros en Querétaro: cómo evitarlos → ancla: «salitre en paredes» | S9: B24 · Cómo calcular cuánta pintura o impermeabilizante necesitas → ancla: «cómo calcular pintura» B30 · Silicón, sellador acrílico y poliuretano: diferencias → ancla: «diferencia entre silicón y sellador acrílico» B31 · Espátulas, llanas y cuñas: guía para acabados perfectos → ancla: «tipos de llanas» B41 · Cómo limpiar y guardar brochas y rodillos para que duren → ancla: «cómo limpiar brochas» B43 · Silicón automotriz vs sellador de construcción → ancla: «silicón de alta temperatura» B56 · Guía de lijas: qué grano usar en madera, metal y agua → ancla: «tipos de lijas» B58 · Impermeabilizante acrílico vs manto: cuál conviene → ancla: «impermeabilizante acrílico vs manto» | T9: (es el pilar) | U9: Conocimiento general estable. No nombrar marcas de pintura ajenas al catálogo (IPESA incluida). Largos de felpa: remitir a la etiqueta. | V9: — | W9: Descarga gratis la guía «Guía rápida: qué herramienta usar según tu pintura» al registrarte en Club 57. | X9: Brief listo
A10: B09 | B10: 46308 | C10: tipos-de-taquetes-tablaroca-concreto-ladrillo-hueco | D10: ="https://ferreteria57.com/blog/"&C10 -> https://ferreteria57.com/blog/tipos-de-taquetes-tablaroca-concreto-ladrillo-hueco | E10: Tipos de taquetes: cuál usar en tablaroca y concreto | F10: =LEN(E10) -> 52 | G10: Guía para elegir el taquete correcto en tablaroca, concreto sólido o ladrillo hueco y evitar que se caigan repisas, pantallas y cuadros. | H10: =LEN(G10) -> 136 | I10: Tipos de taquetes: cuál usar en tablaroca, concreto sólido o ladrillo hueco | J10: tipos de taquetes | K10: taquete para tablaroca; taquete para ladrillo hueco; taquete para concreto; taquete expansivo; taquete mariposa; qué taquete usar | L10: • ¿Qué taquete se usa en tablaroca? • ¿Qué taquete sirve para tabique hueco? • ¿Cómo sé cuánto peso aguanta un taquete? | M10: 1. Por qué se caen las cosas: taquete equivocado, no el tornillo 2. Cómo identificar tu muro (golpe, perforación de prueba, grosor) 3. Taquetes por tipo de muro: concreto sólido, tabique macizo, ladrillo/tabique hueco, tablaroca 4. Plástico, mariposa, expansivo metálico y ancla: cuándo usar cada uno 5. Cómo instalarlos paso a paso (broca, limpieza, profundidad, tornillo) 6. Peso y seguridad: qué no colgar con taquete de plástico 7. Preguntas frecuentes | N10: • Cargas: indicar que la capacidad depende del muro y del fabricante; no inventar kilos • Tabla muro / taquete / broca / uso típico • Enlazar a brocas (mismo diámetro) y a soporte de TV • Reduce reclamos de 'productos que no sirven' por mala instalación | O10: 1.500–2.000 | P10: BlogPosting + BreadcrumbList + FAQPage | Q10: Taquetes plásticos, de nylon, mariposa, expansivos y anclas; tornillos; brocas; detectores y niveles | R10: B02 · Herramientas básicas para el hogar: las 15 esenciales → ancla: «herramientas básicas para el hogar» B03 · Cómo escoger la broca correcta según el material → ancla: «tipos de brocas» | S10: B20 · Cómo instalar un soporte de TV en la pared, nivelado → ancla: «cómo instalar soporte de tv» B44 · Cómo organizar el tablero de herramientas del garaje → ancla: «organizar herramientas» B47 · Herramientas para tablaroca: tu primer muro falso → ancla: «herramientas para tablaroca» | T10: B03 | U10: Conocimiento general. Sin cifras de carga: remitir al empaque del taquete. | V10: Mencionar los tipos de muro frecuentes en casas del Bajío (block, tabique, concreto) sin generalizar. | W10: Descarga gratis la guía «Guía de taquetes por tipo de muro» al registrarte en Club 57. | X10: Brief listo
A11: B10 | B11: 46310 | C11: club-57-como-ganar-puntos-ferreteria-57 | D11: ="https://ferreteria57.com/blog/"&C11 -> https://ferreteria57.com/blog/club-57-como-ganar-puntos-ferreteria-57 | E11: Club 57 de Ferretería 57: cómo ganar puntos y beneficios | F11: =LEN(E11) -> 56 | G11: Descubre Club 57, el programa de lealtad de Ferretería 57: cómo ganar puntos, referir amigos, descargar guías prácticas y acceder a promociones. | H11: =LEN(G11) -> 144 | I11: Club 57: cómo funciona, cómo ganar puntos y qué recibes al registrarte | J11: club 57 ferretería 57 | K11: programa de lealtad ferretería; puntos ferretería querétaro; guías descargables de ferretería; promociones truper | L11: • ¿Cómo me registro en Club 57? • ¿Cómo se ganan puntos en Club 57? • ¿Qué beneficios tienen los miembros de Club 57? | M11: 1. Qué es Club 57 2. Cómo registrarte (en línea o en tienda) 3. Cómo ganar puntos y cuándo puedes canjearlos 4. Recomienda a un amigo: puntos para los dos 5. Guías prácticas en PDF: una por cada artículo del blog 6. Promociones solo para miembros (Liquidaciones del Mes, Promo Truper y Promociones de Temporada) 7. Preguntas frecuentes | N11: • Reglas vigentes al diseñar este brief: 1 punto por cada $50 MXN de subtotal sin envío, canje disponible a los 7 días, referidos 10 y 10 puntos tras la primera compra pagada; recompensas de mercancía promocional, recogida solo en tienda • Los parámetros son configurables en admin: leer los valores vigentes antes de publicar y no hardcodear cifras • No mencionar proveedores técnicos ni límites internos de la plataforma • Explicar sin tecnicismos y con ejemplo ($145 = 2 puntos) | O11: 900–1.300 | P11: BlogPosting + BreadcrumbList + FAQPage | Q11: Club 57 (/cuenta), catálogo de canje, página de promociones de miembros | R11: B01 · Marcas Truper: Pretul, Foset, Volteck y cuál elegir → ancla: «marcas truper» B02 · Herramientas básicas para el hogar: las 15 esenciales → ancla: «herramientas básicas para el hogar» B04 · Tubería PPR, PVC, CPVC o cobre: diferencias y cuál usar → ancla: «diferencia entre tubería ppr y pvc» B05 · Calibre de cable eléctrico para cada electrodoméstico → ancla: «calibre de cable para casa» | S11: B27 · Control de inventarios en ferretería: evita robo hormiga → ancla: «control de inventarios ferretería» B40 · 5 ventajas de comprar en una ferretería de barrio → ancla: «ferretería en querétaro» | T11: B01 | U11: Leer los valores vigentes de Club 57 desde la configuración del admin al redactar; no hardcodear cifras ni mencionar proveedores técnicos. | V11: Tienda física en Querétaro: registro con apoyo del vendedor. | W11: Descarga gratis la guía «Guía de bienvenida a Club 57» al registrarte en Club 57. | X11: Brief listo
A12: B11 | B12: 46312 | C12: como-destapar-tuberia-lavabo-sin-danar-pvc | D12: ="https://ferreteria57.com/blog/"&C12 -> https://ferreteria57.com/blog/como-destapar-tuberia-lavabo-sin-danar-pvc | E12: Cómo destapar el lavabo sin dañar la tubería de PVC | F12: =LEN(E12) -> 51 | G12: Destapa tu lavabo paso a paso con chupón, sonda o limpieza del sifón, sin dañar el PVC y con las precauciones al usar destapacaños. | H12: =LEN(G12) -> 131 | I12: Cómo destapar la tubería del lavabo de forma segura sin dañar el PVC | J12: cómo destapar un lavabo | K12: destapar tubería del lavabo; destapacaños seguro para pvc; chupón para lavabo; limpiar sifón del lavabo; lavabo tapado qué hacer | L12: • ¿Cómo destapar un lavabo sin químicos? • ¿El destapacaños daña la tubería de PVC? • ¿Cómo se limpia el sifón del lavabo? | M12: 1. Por qué se tapa el lavabo (cabello, grasa, jabón, sarro) 2. Método 1: chupón 3. Método 2: limpiar el sifón o trampa 4. Método 3: sonda o guía mecánica 5. Destapacaños químicos: cuándo sí, cuándo no y precauciones 6. Qué evitar (agua hirviendo directa sobre PVC, mezclar productos) 7. Cómo evitar que se vuelva a tapar 8. Preguntas frecuentes | N12: • Orden de menor a mayor agresividad: mecánico antes que químico • Seguridad: guantes, lentes, ventilación y no mezclar productos; seguir la etiqueta • Si hay mal olor persistente o varios desagües tapados, puede ser tubería general: llamar a plomero • Venta cruzada: chupón, sonda, guantes, sifón nuevo, destapacaños | O12: 1.200–1.600 | P12: BlogPosting + BreadcrumbList + FAQPage | Q12: Chupones, sondas, sifones, destapacaños, guantes, lentes de seguridad | R12: B04 · Tubería PPR, PVC, CPVC o cobre: diferencias y cuál usar → ancla: «diferencia entre tubería ppr y pvc» | S12: B13 · Cinta teflón: para qué sirve y cómo se aplica bien → ancla: «cinta teflón» B19 · 10 herramientas para iniciar tu negocio de plomería → ancla: «herramientas de plomero» B29 · Cómo cambiar el sapo y herrajes del tanque del escusado → ancla: «cambiar sapo del tanque del escusado» B32 · Cómo reparar una fuga en la llave mezcladora → ancla: «reparar llave mezcladora» | T12: B04 | U12: Conocimiento general. Seguir la etiqueta de cada destapacaños; sin temperaturas exactas. | V12: — | W12: Descarga gratis la guía «Guía de emergencia: lavabo tapado» al registrarte en Club 57. | X12: Brief listo
A13: B12 | B13: 46315 | C13: como-elegir-candado-anticizalla-exteriores-cortinas | D13: ="https://ferreteria57.com/blog/"&C13 -> https://ferreteria57.com/blog/como-elegir-candado-anticizalla-exteriores-cortinas | E13: Candado anticizalla: cómo elegirlo para exterior | F13: =LEN(E13) -> 48 | G13: Qué hace seguro a un candado anticizalla, cómo elegir tamaño, material y resistencia a la intemperie para cortinas, rejas y portones. | H13: =LEN(G13) -> 133 | I13: Cómo elegir un candado anticizalla para exteriores y cortinas de negocio | J13: candado anticizalla | K13: candado para cortina de negocio; mejor candado para exterior; candado resistente a la intemperie; candado de alta seguridad; candado para reja | L13: • ¿Qué significa que un candado sea anticizalla? • ¿Qué candado es mejor para una cortina metálica? • ¿Los candados de latón o de acero resisten la lluvia? | M13: 1. Qué es un candado anticizalla y por qué importa 2. Partes: cuerpo, grillete (arco), protección del arco y cerradura 3. Materiales y acabados para intemperie 4. Tamaño del cuerpo y diámetro del arco: cómo elegir 5. Cuál usar en cortina, reja, portón o bodega 6. Mantenimiento: lubricar y cuidar el cierre 7. Mini auditoría de seguridad: 8 puntos de tu local o casa 8. Preguntas frecuentes | N13: • Hablar de grados de seguridad solo si hay norma o clasificación del fabricante • No prometer 'inviolable'; hablar de resistencia relativa y disuasión • Enlazar a chapas y candados de moto/bici para completar el clúster • Base para el PDF 'Auditoría de seguridad básica' | O13: 1.500–2.000 | P13: BlogPosting + BreadcrumbList + FAQPage | Q13: Candados de alta seguridad, candados anticizalla, cadenas, lubricantes, pasadores | R13: — | S13: B22 · Fuga de gas en casa: qué hacer y qué revisar → ancla: «fuga de gas qué hacer» B26 · Cómo quitar el óxido de herramientas y metales → ancla: «cómo quitar el óxido» B34 · Guantes de trabajo: nitrilo, carnaza, látex o anticorte → ancla: «guantes de trabajo» B36 · Chapa de sobreponer, embutir o alta seguridad: cuál elegir → ancla: «tipos de chapas para puerta» B45 · EPP en la obra: guía del equipo de protección personal → ancla: «equipo de protección personal en obra» B49 · Candados para moto, bicicleta y rejas: cómo elegir → ancla: «candado para moto» | T13: (es el pilar) | U13: Criterios generales de compra. No prometer «inviolable» ni citar estadísticas; sin grados de seguridad específicos. | V13: Contexto local cualitativo del Bajío (clima, agua, comercio) sin cifras, estadísticas ni fechas. | W13: Descarga gratis la guía «Auditoría de seguridad básica para casa o negocio» al registrarte en Club 57. | X13: Brief listo
... A57: B56 | B57: 46417 | C57: guia-de-lijas-que-grano-usar-madera-metal-agua | D57: ="https://ferreteria57.com/blog/"&C57 -> https://ferreteria57.com/blog/guia-de-lijas-que-grano-usar-madera-metal-agua | E57: Guía de lijas: qué grano usar en madera, metal y agua | F57: =LEN(E57) -> 53 | G57: Qué lija usar y en qué orden de granos para madera, metal o pintura: lijas al agua y secas, con tabla de granos y consejos. | H57: =LEN(G57) -> 123 | I57: Guía rápida de lijas: qué número de grano usar para madera, metal o agua | J57: tipos de lijas | K57: qué grano de lija usar; lija de agua; lija para madera; lija para metal; numeración de lijas | L57: • ¿Qué número de lija uso para madera? • ¿Cuál es la diferencia entre lija seca y lija de agua? • ¿En qué orden se usan las lijas? | M57: 1. Qué significa el número de grano 2. Lijas para madera 3. Lijas para metal 4. Lijas al agua y acabados automotrices 5. Secuencia de granos paso a paso 6. Cómo lijar bien (bloque, presión, polvo) 7. Seguridad 8. Preguntas frecuentes | N57: • Tabla grano → uso, con secuencia • Granos exactos: con empaques reales del catálogo • Complementa pegamentos, pintura y óxido | O57: 1.200–1.600 | P57: BlogPosting + BreadcrumbList + FAQPage | Q57: Lijas secas y de agua, tacos de lijado, lijadoras, mascarillas | R57: B02 · Herramientas básicas para el hogar: las 15 esenciales → ancla: «herramientas básicas para el hogar» B03 · Cómo escoger la broca correcta según el material → ancla: «tipos de brocas» B08 · Brocha o rodillo: cuál usar con pintura vinílica o esmalte → ancla: «brocha o rodillo» B26 · Cómo quitar el óxido de herramientas y metales → ancla: «cómo quitar el óxido» B28 · Tipos de pegamentos: contacto, epóxico y cianoacrilato → ancla: «tipos de pegamentos» B53 · Mantenimiento de herramientas eléctricas: más vida útil → ancla: «mantenimiento de herramientas eléctricas» | S57: — | T57: B02 | U57: Conocimiento general. Granos habituales, sin ser prescriptivos. | V57: — | W57: Descarga gratis la guía «Tabla de lijas: granos y secuencias» al registrarte en Club 57. | X57: Brief listo
A58: B57 | C58: herramientas-manuales-para-preparar-jardin-en-primavera | D58: ="https://ferreteria57.com/blog/"&C58 -> https://ferreteria57.com/blog/herramientas-manuales-para-preparar-jardin-en-primavera | E58: Herramientas para preparar tu jardín en primavera | F58: =LEN(E58) -> 49 | G58: Qué herramientas manuales necesitas para preparar tu jardín o patio en primavera: podar, remover tierra, regar y fertilizar. | H58: =LEN(G58) -> 124 | I58: Catálogo de herramientas manuales para preparar tu jardín o patio en primavera | J58: herramientas de jardinería | K58: tijeras de podar; pala y rastrillo; aspersores y mangueras; fertilizantes; cómo preparar el jardín en primavera | L58: • ¿Qué herramientas básicas necesito para mi jardín? • ¿Qué tijera de podar conviene? • ¿Cuándo es mejor fertilizar? | M58: 1. Planea el jardín 2. Herramientas para remover tierra 3. Poda: tijeras y serruchos 4. Riego: mangueras y aspersores 5. Fertilizantes y cuidados 6. Mantenimiento de herramientas 7. Preguntas frecuentes | N58: • Publicar en febrero–marzo 2027 • Sin recomendaciones agronómicas específicas • Estacional para rotación de inventario | O58: 1.200–1.600 | P58: BlogPosting + BreadcrumbList + FAQPage | Q58: Tijeras de podar, palas, rastrillos, mangueras, aspersores, guantes de jardín | R58: — | S58: B02 · Herramientas básicas para el hogar: las 15 esenciales → ancla: «herramientas básicas para el hogar» B34 · Guantes de trabajo: nitrilo, carnaza, látex o anticorte → ancla: «guantes de trabajo» B52 · Mangueras industriales de aire y agua vs de jardín → ancla: «manguera industrial» | T58: B02 | U58: Conocimiento general. Sin recomendaciones agronómicas específicas. | V58: Contexto local cualitativo del Bajío (clima, agua, comercio) sin cifras, estadísticas ni fechas. | W58: Descarga gratis la guía «Calendario de jardín: primavera» al registrarte en Club 57. | X58: Brief listo
A59: B58 | C59: impermeabilizante-acrilico-vs-manto-prefabricado | D59: ="https://ferreteria57.com/blog/"&C59 -> https://ferreteria57.com/blog/impermeabilizante-acrilico-vs-manto-prefabricado | E59: Impermeabilizante acrílico vs manto: cuál conviene | F59: =LEN(E59) -> 50 | G59: Compara impermeabilizantes acrílicos y prefabricados (manto): costo, duración, aplicación y mantenimiento para tu azotea. | H59: =LEN(G59) -> 121 | I59: Impermeabilizantes acrílicos vs prefabricados (manto): cuál conviene más | J59: impermeabilizante acrílico vs manto | K59: tipos de impermeabilizante; impermeabilizante para azotea; manto asfáltico; cuánto dura un impermeabilizante; cómo impermeabilizar una losa | L59: • ¿Qué es mejor, impermeabilizante acrílico o manto? • ¿Cuánto dura un impermeabilizante? • ¿Cómo se prepara la azotea antes de impermeabilizar? | M59: 1. Por qué impermeabilizar 2. Acrílico: cómo funciona 3. Manto prefabricado: cómo funciona 4. Comparación: costo, duración, aplicación, mantenimiento 5. Preparación de la azotea 6. Cuándo conviene cada uno 7. Preguntas frecuentes | N59: • Publicar en marzo 2027, antes de la temporada de lluvias • Duración: solo con garantía del fabricante • Enlazar a salitre y cálculo de pintura/ impermeabilizante | O59: 1.200–1.600 | P59: BlogPosting + BreadcrumbList + FAQPage | Q59: Impermeabilizantes acrílicos, mantos, reforzantes, selladores, brochas y rodillos | R59: — | S59: B06 · Salitre y humedad en muros en Querétaro: cómo evitarlos → ancla: «salitre en paredes» B08 · Brocha o rodillo: cuál usar con pintura vinílica o esmalte → ancla: «brocha o rodillo» B24 · Cómo calcular cuánta pintura o impermeabilizante necesitas → ancla: «cómo calcular pintura» B30 · Silicón, sellador acrílico y poliuretano: diferencias → ancla: «diferencia entre silicón y sellador acrílico» | T59: B08 | U59: Conocimiento general. Duración: remitir a la garantía del fabricante. | V59: Contexto local cualitativo del Bajío (clima, agua, comercio) sin cifras, estadísticas ni fechas. | W59: Descarga gratis la guía «Guía de impermeabilización de azotea» al registrarte en Club 57. | X59: Brief listo

Sheet Guías PDF
A1: ID | B1: Fecha | C1: Artículo (H1) | D1: Título de la guía | E1: Nombre de archivo | F1: Formato | G1: Páginas | H1: Contenido por página | I1: Regla de redacción | J1: Texto de entrega (Club 57) | K1: Estado PDF
A2: B01 | B2: 46304 | C2: Truper, Pretul, Foset, Volteck y más: guía de marcas para elegir herramienta y material | D2: Guía de marcas Truper: cuál elegir según tu trabajo | E2: guia-marcas-truper-pretul-foset-volteck-guia.pdf | F2: Tabla comparativa + criterios de decisión | G2: 2 | H2: Pág. 1: las 7 marcas en una tabla (línea, para quién, ejemplo de producto). Pág. 2: 'Elige en 3 preguntas' (frecuencia de uso, exigencia, presupuesto) y tabla tarea→marca sugerida. | I2: Escribir solo con lo que muestra el catálogo del sitio (nombres de productos y categorías). No afirmar qué línea cubre cada marca ni garantías específicas; remitir a la etiqueta o ficha de cada producto. | J2: Tu guía «Guía de marcas Truper: cuál elegir según tu trabajo» ya está disponible en tu cuenta de Club 57. | K2: Pendiente
A3: B02 | B3: 46304 | C3: Kit básico de herramientas para el hogar: las 15 que sí necesitas (y cuáles dejar para después) | D3: Checklist: caja de herramientas básica del hogar | E3: guia-kit-basico-herramientas-hogar.pdf | F3: Checklist imprimible en 3 niveles | G3: 2 | H3: Pág. 1: checklist de las 15 herramientas con casillas, por nivel. Pág. 2: 'qué buscar al comprar' (1 línea por herramienta) y espacio para anotar medidas de la casa. | I3: Conocimiento general estable. Sin precios; enlazar solo herramientas que existan en el catálogo. | J3: Tu guía «Checklist: caja de herramientas básica del hogar» ya está disponible en tu cuenta de Club 57. | K3: Pendiente
A4: B03 | B4: 46304 | C4: Cómo escoger el tamaño y tipo de broca correcto para cada material | D4: Tabla rápida: broca, taquete y tornillo por material | E4: guia-como-escoger-broca-correcta-para-cada-material.pdf | F4: Tabla de consulta rápida | G4: 1 | H4: 1 página tipo cartel: matriz Material × Broca × Taquete × Tornillo × Consejo; recuadro 'Antes de taladrar' (marcar, detector de tubos/cables, velocidad). | I4: Conocimiento general estable. Diámetros y velocidades: remitir al empaque de la broca y al manual del taladro. | J4: Tu guía «Tabla rápida: broca, taquete y tornillo por material» ya está disponible en tu cuenta de Club 57. | K4: Pendiente
A5: B04 | B5: 46304 | C5: PPR, PVC, CPVC o cobre: diferencias entre tuberías y cuál conviene en tu proyecto | D5: Comparador de tuberías: PPR, PVC, CPVC y cobre | E5: guia-diferencias-tuberia-ppr-pvc-cpvc-cobre.pdf | F5: Tabla comparativa + árbol de decisión | G5: 2 | H5: Pág. 1: tabla comparativa (uso, temperatura, unión, herramienta, costo relativo). Pág. 2: árbol de decisión '¿qué tubería uso?' en texto y flechas vectoriales + lista de materiales por tipo de unión. | I5: Comparar por características generales (costo relativo, tipo de unión, uso). Sin límites numéricos de temperatura o presión: remitir a la ficha del fabricante. | J5: Tu guía «Comparador de tuberías: PPR, PVC, CPVC y cobre» ya está disponible en tu cuenta de Club 57. | K5: Pendiente
A6: B05 | B6: 46304 | C6: Calibre de cables eléctricos: cuál usar para cada electrodoméstico y cada circuito | D6: Tabla de calibres: qué cable para cada aparato | E6: guia-calibre-de-cable-electrico-para-cada-electrodomestico.pdf | F6: Tabla de consulta + ejemplo de cálculo | G6: 2 | H6: Pág. 1: tabla orientativa calibre ↔ amperes ↔ usos comunes. Pág. 2: cálculo paso a paso (watts→amperes→calibre) con 3 ejemplos y aviso de seguridad. | I6: Usar la regla práctica estándar 14/12/10 AWG ↔ 15/20/30 A, presentada como orientativa. Sin números de norma; indicar que un electricista valida la instalación. | J6: Tu guía «Tabla de calibres: qué cable para cada aparato» ya está disponible en tu cuenta de Club 57. | K6: Pendiente
A7: B06 | B7: 46304 | C7: Salitre y humedad en muros en Querétaro: cómo protegerlos y eliminarlos paso a paso | D7: Guía visual: salitre y humedad, diagnóstico y reparación | E7: guia-salitre-y-humedad-en-muros-queretaro.pdf | F7: Guía de diagnóstico + checklist | G7: 2 | H7: Pág. 1: diagnóstico (¿salitre, moho o fuga?) en preguntas sí/no. Pág. 2: checklist de reparación paso a paso con materiales y tiempos de secado. | I7: Procedimiento general. Tiempos de secado y dosificación: remitir a la etiqueta de cada producto. Sin fechas ni cifras de clima. | J7: Tu guía «Guía visual: salitre y humedad, diagnóstico y reparación» ya está disponible en tu cuenta de Club 57. | K7: Pendiente
A8: B07 | B8: 46304 | C8: Tinaco o cisterna en Querétaro: qué considerar para instalarlo y no quedarte sin agua | D8: Checklist de instalación de tinaco o cisterna | E8: guia-instalar-tinaco-o-cisterna-queretaro.pdf | F8: Checklist + mini calculadora en papel | G8: 2 | H8: Pág. 1: cálculo de capacidad (tabla por personas) y lista de componentes. Pág. 2: checklist de instalación y de limpieza semestral. | I8: Cálculo con un supuesto ilustrativo declarado como ejemplo (p. ej. consumo por persona), invitando al lector a ajustarlo. Hablar de cortes de agua en general, sin datos de colonias. | J8: Tu guía «Checklist de instalación de tinaco o cisterna» ya está disponible en tu cuenta de Club 57. | K8: Pendiente
A9: B08 | B9: 46304 | C9: Brocha o rodillo: qué necesitas según la pintura (vinílica vs esmalte) | D9: Guía rápida: qué herramienta usar según tu pintura | E9: guia-brocha-o-rodillo-segun-pintura-vinilica-esmalte.pdf | F9: Tabla de decisión | G9: 1 | H9: 1 página: tabla Superficie × Tipo de pintura × Herramienta × Consejo; checklist de materiales para pintar un cuarto. | I9: Conocimiento general estable. No nombrar marcas de pintura ajenas al catálogo (IPESA incluida). Largos de felpa: remitir a la etiqueta. | J9: Tu guía «Guía rápida: qué herramienta usar según tu pintura» ya está disponible en tu cuenta de Club 57. | K9: Pendiente
A10: B09 | B10: 46308 | C10: Tipos de taquetes: cuál usar en tablaroca, concreto sólido o ladrillo hueco | D10: Guía de taquetes por tipo de muro | E10: guia-tipos-de-taquetes-tablaroca-concreto-ladrillo-hueco.pdf | F10: Tabla de consulta + checklist de instalación | G10: 1 | H10: 1 página: tabla Tipo de muro × Taquete × Broca × Tornillo × Uso; checklist de 6 pasos de instalación; recuadro 'No cuelgues esto con taquete de plástico'. | I10: Conocimiento general. Sin cifras de carga: remitir al empaque del taquete. | J10: Tu guía «Guía de taquetes por tipo de muro» ya está disponible en tu cuenta de Club 57. | K10: Pendiente
A11: B10 | B11: 46310 | C11: Club 57: cómo funciona, cómo ganar puntos y qué recibes al registrarte | D11: Guía de bienvenida a Club 57 | E11: guia-club-57-como-ganar-puntos-ferreteria-57.pdf | F11: Guía rápida de bienvenida | G11: 2 | H11: Pág. 1: cómo funciona Club 57 (ganar, esperar, canjear, referir) con ejemplo numérico. Pág. 2: índice de guías PDF disponibles y cómo acceder a las promociones de miembros. | I11: Leer los valores vigentes de Club 57 desde la configuración del admin al redactar; no hardcodear cifras ni mencionar proveedores técnicos. | J11: Tu guía «Guía de bienvenida a Club 57» ya está disponible en tu cuenta de Club 57. | K11: Pendiente
A12: B11 | B12: 46312 | C12: Cómo destapar la tubería del lavabo de forma segura sin dañar el PVC | D12: Guía de emergencia: lavabo tapado | E12: guia-como-destapar-tuberia-lavabo-sin-danar-pvc.pdf | F12: Guía de pasos + checklist de materiales | G12: 1 | H12: 1 página: árbol de decisión (¿qué intento primero?), pasos de cada método y recuadro de seguridad con químicos. | I12: Conocimiento general. Seguir la etiqueta de cada destapacaños; sin temperaturas exactas. | J12: Tu guía «Guía de emergencia: lavabo tapado» ya está disponible en tu cuenta de Club 57. | K12: Pendiente
A13: B12 | B13: 46315 | C13: Cómo elegir un candado anticizalla para exteriores y cortinas de negocio | D13: Auditoría de seguridad básica para casa o negocio | E13: guia-como-elegir-candado-anticizalla-exteriores-cortinas.pdf | F13: Checklist de auditoría | G13: 2 | H13: Pág. 1: checklist de 20 puntos (accesos, candados, iluminación, cortinas, rutinas). Pág. 2: guía de selección de candado por uso y plan de mejora priorizado. | I13: Criterios generales de compra. No prometer «inviolable» ni citar estadísticas; sin grados de seguridad específicos. | J13: Tu guía «Auditoría de seguridad básica para casa o negocio» ya está disponible en tu cuenta de Club 57. | K13: Pendiente
... A57: B56 | B57: 46417 | C57: Guía rápida de lijas: qué número de grano usar para madera, metal o agua | D57: Tabla de lijas: granos y secuencias | E57: guia-guia-de-lijas-que-grano-usar-madera-metal-agua.pdf | F57: Tabla de consulta | G57: 1 | H57: 1 página: tabla grano × uso × secuencia por proyecto. | I57: Conocimiento general. Granos habituales, sin ser prescriptivos. | J57: Tu guía «Tabla de lijas: granos y secuencias» ya está disponible en tu cuenta de Club 57. | K57: Pendiente
A58: B57 | C58: Catálogo de herramientas manuales para preparar tu jardín o patio en primavera | D58: Calendario de jardín: primavera | E58: guia-herramientas-manuales-para-preparar-jardin-en-primavera.pdf | F58: Calendario + checklist | G58: 1 | H58: 1 página: checklist y calendario de tareas. | I58: Conocimiento general. Sin recomendaciones agronómicas específicas. | J58: Tu guía «Calendario de jardín: primavera» ya está disponible en tu cuenta de Club 57. | K58: Pendiente
A59: B58 | C59: Impermeabilizantes acrílicos vs prefabricados (manto): cuál conviene más | D59: Guía de impermeabilización de azotea | E59: guia-impermeabilizante-acrilico-vs-manto-prefabricado.pdf | F59: Guía + checklist | G59: 2 | H59: Pág. 1: comparativa. Pág. 2: checklist de preparación y aplicación. | I59: Conocimiento general. Duración: remitir a la garantía del fabricante. | J59: Tu guía «Guía de impermeabilización de azotea» ya está disponible en tu cuenta de Club 57. | K59: Pendiente

Sheet Mapa de enlaces
A1: ID enlace | B1: Origen (donde va el enlace) | C1: Título del origen | D1: Destino | E1: Título del destino | F1: Texto ancla sugerido | G1: Tipo | H1: Cuándo se agrega | I1: Fecha | J1: Estado
A2: EN001 | B2: B01 | C2: Marcas Truper: Pretul, Foset, Volteck y cuál elegir | D2: B02 | E2: Herramientas básicas para el hogar: las 15 esenciales | F2: herramientas básicas para el hogar | G2: Relacionado | H2: Lanzamiento (mismo día) | I2: 46304 | J2: Pendiente
A3: EN002 | B3: B02 | C3: Herramientas básicas para el hogar: las 15 esenciales | D3: B01 | E3: Marcas Truper: Pretul, Foset, Volteck y cuál elegir | F3: marcas truper | G3: Relacionado | H3: Lanzamiento (mismo día) | I3: 46304 | J3: Pendiente
A4: EN003 | B4: B01 | C4: Marcas Truper: Pretul, Foset, Volteck y cuál elegir | D4: B03 | E4: Cómo escoger la broca correcta según el material | F4: tipos de brocas | G4: Relacionado | H4: Lanzamiento (mismo día) | I4: 46304 | J4: Pendiente
A5: EN004 | B5: B02 | C5: Herramientas básicas para el hogar: las 15 esenciales | D5: B03 | E5: Cómo escoger la broca correcta según el material | F5: tipos de brocas | G5: Relacionado | H5: Lanzamiento (mismo día) | I5: 46304 | J5: Pendiente
A6: EN005 | B6: B03 | C6: Cómo escoger la broca correcta según el material | D6: B01 | E6: Marcas Truper: Pretul, Foset, Volteck y cuál elegir | F6: marcas truper | G6: Relacionado | H6: Lanzamiento (mismo día) | I6: 46304 | J6: Pendiente
A7: EN006 | B7: B03 | C7: Cómo escoger la broca correcta según el material | D7: B02 | E7: Herramientas básicas para el hogar: las 15 esenciales | F7: herramientas básicas para el hogar | G7: Relacionado | H7: Lanzamiento (mismo día) | I7: 46304 | J7: Pendiente
A8: EN007 | B8: B01 | C8: Marcas Truper: Pretul, Foset, Volteck y cuál elegir | D8: B05 | E8: Calibre de cable eléctrico para cada electrodoméstico | F8: calibre de cable para casa | G8: Relacionado | H8: Lanzamiento (mismo día) | I8: 46304 | J8: Pendiente
A9: EN008 | B9: B05 | C9: Calibre de cable eléctrico para cada electrodoméstico | D9: B01 | E9: Marcas Truper: Pretul, Foset, Volteck y cuál elegir | F9: marcas truper | G9: Relacionado | H9: Lanzamiento (mismo día) | I9: 46304 | J9: Pendiente
A10: EN009 | B10: B04 | C10: Tubería PPR, PVC, CPVC o cobre: diferencias y cuál usar | D10: B07 | E10: Tinaco o cisterna en Querétaro: guía de instalación | F10: instalar tinaco | G10: Pilar de clúster ↔ satélite | H10: Lanzamiento (mismo día) | I10: 46304 | J10: Pendiente
A11: EN010 | B11: B07 | C11: Tinaco o cisterna en Querétaro: guía de instalación | D11: B04 | E11: Tubería PPR, PVC, CPVC o cobre: diferencias y cuál usar | F11: diferencia entre tubería ppr y pvc | G11: Pilar de clúster ↔ satélite | H11: Lanzamiento (mismo día) | I11: 46304 | J11: Pendiente
A12: EN011 | B12: B01 | C12: Marcas Truper: Pretul, Foset, Volteck y cuál elegir | D12: B08 | E12: Brocha o rodillo: cuál usar con pintura vinílica o esmalte | F12: brocha o rodillo | G12: Relacionado | H12: Lanzamiento (mismo día) | I12: 46304 | J12: Pendiente
A13: EN012 | B13: B06 | C13: Salitre y humedad en muros en Querétaro: cómo evitarlos | D13: B08 | E13: Brocha o rodillo: cuál usar con pintura vinílica o esmalte | F13: brocha o rodillo | G13: Pilar de clúster ↔ satélite | H13: Lanzamiento (mismo día) | I13: 46304 | J13: Pendiente
... A315: EN314 | B315: B56 | C315: Guía de lijas: qué grano usar en madera, metal y agua | D315: B53 | E315: Mantenimiento de herramientas eléctricas: más vida útil | F315: mantenimiento de herramientas eléctricas | G315: Relacionado | H315: Al redactar B56 | I315: 46417 | J315: Pendiente
A316: EN315 | B316: B02 | C316: Herramientas básicas para el hogar: las 15 esenciales | D316: B57 | E316: Herramientas para preparar tu jardín en primavera | F316: herramientas de jardinería | G316: Pilar de clúster ↔ satélite | H316: Cuando se publique el artículo de Reserva | J316: Pendiente
A317: EN316 | B317: B34 | C317: Guantes de trabajo: nitrilo, carnaza, látex o anticorte | D317: B57 | E317: Herramientas para preparar tu jardín en primavera | F317: herramientas de jardinería | G317: Relacionado | H317: Cuando se publique el artículo de Reserva | J317: Pendiente
A318: EN317 | B318: B52 | C318: Mangueras industriales de aire y agua vs de jardín | D318: B57 | E318: Herramientas para preparar tu jardín en primavera | F318: herramientas de jardinería | G318: Relacionado | H318: Cuando se publique el artículo de Reserva | J318: Pendiente
A319: EN318 | B319: B57 | C319: Herramientas para preparar tu jardín en primavera | D319: B02 | E319: Herramientas básicas para el hogar: las 15 esenciales | F319: herramientas básicas para el hogar | G319: Pilar de clúster ↔ satélite | H319: Cuando se publique el artículo de Reserva | J319: Pendiente
A320: EN319 | B320: B57 | C320: Herramientas para preparar tu jardín en primavera | D320: B34 | E320: Guantes de trabajo: nitrilo, carnaza, látex o anticorte | F320: guantes de trabajo | G320: Relacionado | H320: Cuando se publique el artículo de Reserva | J320: Pendiente
A321: EN320 | B321: B57 | C321: Herramientas para preparar tu jardín en primavera | D321: B52 | E321: Mangueras industriales de aire y agua vs de jardín | F321: manguera industrial | G321: Relacionado | H321: Cuando se publique el artículo de Reserva | J321: Pendiente
A322: EN321 | B322: B06 | C322: Salitre y humedad en muros en Querétaro: cómo evitarlos | D322: B58 | E322: Impermeabilizante acrílico vs manto: cuál conviene | F322: impermeabilizante acrílico vs manto | G322: Relacionado | H322: Cuando se publique el artículo de Reserva | J322: Pendiente
A323: EN322 | B323: B08 | C323: Brocha o rodillo: cuál usar con pintura vinílica o esmalte | D323: B58 | E323: Impermeabilizante acrílico vs manto: cuál conviene | F323: impermeabilizante acrílico vs manto | G323: Pilar de clúster ↔ satélite | H323: Cuando se publique el artículo de Reserva | J323: Pendiente
A324: EN323 | B324: B24 | C324: Cómo calcular cuánta pintura o impermeabilizante necesitas | D324: B58 | E324: Impermeabilizante acrílico vs manto: cuál conviene | F324: impermeabilizante acrílico vs manto | G324: Relacionado | H324: Cuando se publique el artículo de Reserva | J324: Pendiente
A325: EN324 | B325: B30 | C325: Silicón, sellador acrílico y poliuretano: diferencias | D325: B58 | E325: Impermeabilizante acrílico vs manto: cuál conviene | F325: impermeabilizante acrílico vs manto | G325: Relacionado | H325: Cuando se publique el artículo de Reserva | J325: Pendiente
A326: EN325 | B326: B58 | C326: Impermeabilizante acrílico vs manto: cuál conviene | D326: B06 | E326: Salitre y humedad en muros en Querétaro: cómo evitarlos | F326: salitre en paredes | G326: Relacionado | H326: Cuando se publique el artículo de Reserva | J326: Pendiente
A327: EN326 | B327: B58 | C327: Impermeabilizante acrílico vs manto: cuál conviene | D327: B08 | E327: Brocha o rodillo: cuál usar con pintura vinílica o esmalte | F327: brocha o rodillo | G327: Pilar de clúster ↔ satélite | H327: Cuando se publique el artículo de Reserva | J327: Pendiente
... A329: EN328 | B329: B58 | C329: Impermeabilizante acrílico vs manto: cuál conviene | D329: B30 | E329: Silicón, sellador acrílico y poliuretano: diferencias | F329: diferencia entre silicón y sellador acrílico | G329: Relacionado | H329: Cuando se publique el artículo de Reserva | J329: Pendiente

Sheet Resumen
A1: Resumen del backlog – Blog Ferretería 57
A3: Clúster | B3: Pilar | C3: Fondo | D3: Corto | E3: Fin de semana | F3: Total programado | G3: Reserva | H3: Total
A4: Plomería y agua | B4: =COUNTIFS(Backlog!$E$2:$E$59,$A4,Backlog!$G$2:$G$59,"Pilar") -> 2 | C4: =COUNTIFS(Backlog!$E$2:$E$59,$A4,Backlog!$G$2:$G$59,"Fondo") -> 2 | D4: =COUNTIFS(Backlog!$E$2:$E$59,$A4,Backlog!$G$2:$G$59,"Corto") -> 1 | E4: =COUNTIFS(Backlog!$E$2:$E$59,$A4,Backlog!$G$2:$G$59,"Fin de semana") -> 6 | F4: =SUM(B4:E4) -> 11 | G4: =COUNTIFS(Backlog!$E$2:$E$59,$A4,Backlog!$G$2:$G$59,"Reserva") -> 0 | H4: =F4+G4 -> 11
A5: Electricidad e iluminación | B5: =COUNTIFS(Backlog!$E$2:$E$59,$A5,Backlog!$G$2:$G$59,"Pilar") -> 1 | C5: =COUNTIFS(Backlog!$E$2:$E$59,$A5,Backlog!$G$2:$G$59,"Fondo") -> 2 | D5: =COUNTIFS(Backlog!$E$2:$E$59,$A5,Backlog!$G$2:$G$59,"Corto") -> 1 | E5: =COUNTIFS(Backlog!$E$2:$E$59,$A5,Backlog!$G$2:$G$59,"Fin de semana") -> 2 | F5: =SUM(B5:E5) -> 6 | G5: =COUNTIFS(Backlog!$E$2:$E$59,$A5,Backlog!$G$2:$G$59,"Reserva") -> 0 | H5: =F5+G5 -> 6
A6: Pintura, sellado e impermeabilización | B6: =COUNTIFS(Backlog!$E$2:$E$59,$A6,Backlog!$G$2:$G$59,"Pilar") -> 2 | C6: =COUNTIFS(Backlog!$E$2:$E$59,$A6,Backlog!$G$2:$G$59,"Fondo") -> 2 | D6: =COUNTIFS(Backlog!$E$2:$E$59,$A6,Backlog!$G$2:$G$59,"Corto") -> 1 | E6: =COUNTIFS(Backlog!$E$2:$E$59,$A6,Backlog!$G$2:$G$59,"Fin de semana") -> 1 | F6: =SUM(B6:E6) -> 6 | G6: =COUNTIFS(Backlog!$E$2:$E$59,$A6,Backlog!$G$2:$G$59,"Reserva") -> 1 | H6: =F6+G6 -> 7
A7: Construcción, fijación y materiales | B7: =COUNTIFS(Backlog!$E$2:$E$59,$A7,Backlog!$G$2:$G$59,"Pilar") -> 1 | C7: =COUNTIFS(Backlog!$E$2:$E$59,$A7,Backlog!$G$2:$G$59,"Fondo") -> 4 | D7: =COUNTIFS(Backlog!$E$2:$E$59,$A7,Backlog!$G$2:$G$59,"Corto") -> 1 | E7: =COUNTIFS(Backlog!$E$2:$E$59,$A7,Backlog!$G$2:$G$59,"Fin de semana") -> 2 | F7: =SUM(B7:E7) -> 8 | G7: =COUNTIFS(Backlog!$E$2:$E$59,$A7,Backlog!$G$2:$G$59,"Reserva") -> 0 | H7: =F7+G7 -> 8
A8: Herramientas y mantenimiento | B8: =COUNTIFS(Backlog!$E$2:$E$59,$A8,Backlog!$G$2:$G$59,"Pilar") -> 1 | C8: =COUNTIFS(Backlog!$E$2:$E$59,$A8,Backlog!$G$2:$G$59,"Fondo") -> 1 | D8: =COUNTIFS(Backlog!$E$2:$E$59,$A8,Backlog!$G$2:$G$59,"Corto") -> 3 | E8: =COUNTIFS(Backlog!$E$2:$E$59,$A8,Backlog!$G$2:$G$59,"Fin de semana") -> 5 | F8: =SUM(B8:E8) -> 10 | G8: =COUNTIFS(Backlog!$E$2:$E$59,$A8,Backlog!$G$2:$G$59,"Reserva") -> 1 | H8: =F8+G8 -> 11
A9: Seguridad y protección | B9: =COUNTIFS(Backlog!$E$2:$E$59,$A9,Backlog!$G$2:$G$59,"Pilar") -> 0 | C9: =COUNTIFS(Backlog!$E$2:$E$59,$A9,Backlog!$G$2:$G$59,"Fondo") -> 3 | D9: =COUNTIFS(Backlog!$E$2:$E$59,$A9,Backlog!$G$2:$G$59,"Corto") -> 3 | E9: =COUNTIFS(Backlog!$E$2:$E$59,$A9,Backlog!$G$2:$G$59,"Fin de semana") -> 0 | F9: =SUM(B9:E9) -> 6 | G9: =COUNTIFS(Backlog!$E$2:$E$59,$A9,Backlog!$G$2:$G$59,"Reserva") -> 0 | H9: =F9+G9 -> 6
A10: Oficios y negocio ferretero | B10: =COUNTIFS(Backlog!$E$2:$E$59,$A10,Backlog!$G$2:$G$59,"Pilar") -> 0 | C10: =COUNTIFS(Backlog!$E$2:$E$59,$A10,Backlog!$G$2:$G$59,"Fondo") -> 2 | D10: =COUNTIFS(Backlog!$E$2:$E$59,$A10,Backlog!$G$2:$G$59,"Corto") -> 4 | E10: =COUNTIFS(Backlog!$E$2:$E$59,$A10,Backlog!$G$2:$G$59,"Fin de semana") -> 0 | F10: =SUM(B10:E10) -> 6 | G10: =COUNTIFS(Backlog!$E$2:$E$59,$A10,Backlog!$G$2:$G$59,"Reserva") -> 0 | H10: =F10+G10 -> 6
A11: Marca y Club 57 | B11: =COUNTIFS(Backlog!$E$2:$E$59,$A11,Backlog!$G$2:$G$59,"Pilar") -> 1 | C11: =COUNTIFS(Backlog!$E$2:$E$59,$A11,Backlog!$G$2:$G$59,"Fondo") -> 0 | D11: =COUNTIFS(Backlog!$E$2:$E$59,$A11,Backlog!$G$2:$G$59,"Corto") -> 2 | E11: =COUNTIFS(Backlog!$E$2:$E$59,$A11,Backlog!$G$2:$G$59,"Fin de semana") -> 0 | F11: =SUM(B11:E11) -> 3 | G11: =COUNTIFS(Backlog!$E$2:$E$59,$A11,Backlog!$G$2:$G$59,"Reserva") -> 0 | H11: =F11+G11 -> 3
A12: Total | B12: =SUM(B4:B11) -> 8 | C12: =SUM(C4:C11) -> 16 | D12: =SUM(D4:D11) -> 16 | E12: =SUM(E4:E11) -> 16 | F12: =SUM(F4:F11) -> 56 | G12: =SUM(G4:G11) -> 2 | H12: =SUM(H4:H11) -> 58
A15: Periodo | B15: Desde | C15: Hasta | D15: Artículos | E15: Incluidos en cuota (máx. 13/mes) | F15: Excedente sobre 13 | G15: Observación
A16: Lanzamiento (vie 9-oct-2026) | B16: 46304 | C16: 46304 | D16: =COUNTIFS(Backlog!$C$2:$C$59,">="&B16,Backlog!$C$2:$C$59,"<="&C16) -> 8 | E16: n/a | F16: n/a | G16: 8 artículos iniciales para poblar el blog; se asume parte de la integración.
A17: Octubre 2026 (ritmo regular desde 13-oct) | B17: 46305 | C17: 46326 | D17: =COUNTIFS(Backlog!$C$2:$C$59,">="&B17,Backlog!$C$2:$C$59,"<="&C17) -> 9 | E17: 13 | F17: =MAX(0,D17-E17) -> 0 | G17: Martes, jueves y sábado.
A18: Noviembre 2026 | B18: 46327 | C18: 46356 | D18: =COUNTIFS(Backlog!$C$2:$C$59,">="&B18,Backlog!$C$2:$C$59,"<="&C18) -> 12 | E18: 13 | F18: =MAX(0,D18-E18) -> 0
A19: Diciembre 2026 | B19: 46357 | C19: 46387 | D19: =COUNTIFS(Backlog!$C$2:$C$59,">="&B19,Backlog!$C$2:$C$59,"<="&C19) -> 14 | E19: 13 | F19: =MAX(0,D19-E19) -> 1 | G19: 5 martes y 5 jueves: 14 piezas. Jueves 24 y 31 son piezas ligeras; si se pasa una a Reserva queda en 13.
A20: Enero 2027 (hasta sáb 30-ene) | B20: 46388 | C20: 46418 | D20: =COUNTIFS(Backlog!$C$2:$C$59,">="&B20,Backlog!$C$2:$C$59,"<="&C20) -> 13 | E20: 13 | F20: =MAX(0,D20-E20) -> 0
A21: Total programado | D21: =SUM(D16:D20) -> 56
A22: Reserva (sin fecha) | D22: =COUNTIFS(Backlog!$B$2:$B$59,"Reserva") -> 2
A23: Total backlog | D23: =D21+D22 -> 58
A24: Control: coincide con total por clúster | D24: =IF(D23=H12,"OK","REVISAR") -> OK
A27: Día de publicación | B27: Artículos
A28: Martes | B28: =COUNTIFS(Backlog!$D$2:$D$59,"martes") -> 16
A29: Jueves | B29: =COUNTIFS(Backlog!$D$2:$D$59,"jueves") -> 16
A30: Viernes | B30: =COUNTIFS(Backlog!$D$2:$D$59,"viernes") -> 8
A31: Sábado | B31: =COUNTIFS(Backlog!$D$2:$D$59,"sábado") -> 16
A32: Total | B32: =SUM(B28:B31) -> 56
A35: Estado | B35: Artículos
A36: Backlog | B36: =COUNTIF(Backlog!$P$2:$P$59,"Backlog") -> 58
A37: Brief listo | B37: =COUNTIF(Backlog!$P$2:$P$59,"Brief listo") -> 0
A38: Borrador | B38: =COUNTIF(Backlog!$P$2:$P$59,"Borrador") -> 0
A39: En revisión | B39: =COUNTIF(Backlog!$P$2:$P$59,"En revisión") -> 0
A40: Programado | B40: =COUNTIF(Backlog!$P$2:$P$59,"Programado") -> 0
A41: Publicado | B41: =COUNTIF(Backlog!$P$2:$P$59,"Publicado") -> 0
A42: Descartado | B42: =COUNTIF(Backlog!$P$2:$P$59,"Descartado") -> 0
A43: Total | B43: =SUM(B36:B42) -> 58
A46: Control de enlazado | B46: Valor
A47: Enlaces totales (ida y vuelta) | B47: =COUNTA('Mapa de enlaces'!A2:A329) -> 328
A48: Enlaces pendientes | B48: =COUNTIF('Mapa de enlaces'!J2:J329,"Pendiente") -> 328
A49: Artículos sin enlaces entrantes | B49: =SUMPRODUCT(--(COUNTIF('Mapa de enlaces'!D2:D329,Backlog!A2:A59)=0)) -> 0
A50: Artículos sin enlaces salientes | B50: =SUMPRODUCT(--(COUNTIF('Mapa de enlaces'!B2:B329,Backlog!A2:A59)=0)) -> 0

Sheet Especificaciones
A1: Tema | B1: Especificación
A2: Alcance | B2: Blog de Ferretería 57 en ferreteria57.com/blog (dominio canónico sin www; www redirige a él). Objetivo: posicionamiento orgánico en Querétaro y autoridad técnica para dueños de ferreterías, oficios y personas comunes. El posicionamiento en primera página toma de 3 a 6 meses.
A3: Idioma y voz | B3: Español de México, trato de tú, claro y sin tecnicismos no explicados. Voz de ferretero experto y cercano. Sin promesas absolutas ni exageraciones. No denigrar marcas ni competidores.
A4: Autoría y confianza | B4: Autor visible: «Equipo Ferretería 57». Fecha de publicación y de última actualización visibles. Pie con aviso: la información es orientativa y no sustituye a un profesional en temas eléctricos, de gas o estructurales.
A5: Sin imágenes | B5: Los artículos no llevan fotografías ni imágenes generadas. Mismo estilo que https://agents.publifix.net/recursos: tipografía, tablas, listas, cajas de aviso y, cuando ayude, diagramas vectoriales (SVG/CSS) hechos en código. Las tablas son HTML semántico.
A6: URL | B6: /blog/{slug}. El slug está en la hoja «Briefs SEO», en minúsculas, sin acentos y con guiones. No cambiar el slug después de publicar; si es inevitable, redirección 301.
A7: Title tag | B7: Máximo 60 caracteres, incluye la keyword principal al inicio cuando sea natural. No se agrega sufijo de marca (la marca va en og:site_name). Validado en la hoja «Briefs SEO» (columna Car.).
A8: Meta description | B8: Entre 120 y 155 caracteres, con keyword y un beneficio claro. Validada en la hoja «Briefs SEO».
A9: Encabezados | B9: Un solo H1 (campo H1 del brief). Los H2 de la hoja son la estructura mínima; se pueden añadir H3. La keyword principal aparece en el H1, en el primer párrafo y en al menos un H2. Respuesta directa a la búsqueda en las primeras 100 palabras.
A10: Extensión | B10: Pilar 2.000–2.500 palabras; Fondo (martes) 1.500–2.000; Corto (jueves) 900–1.300; Fin de semana (sábado) 1.200–1.600. La calidad pesa más que la longitud: no rellenar.
A11: Sección FAQ | B11: Responder las preguntas de la columna «Preguntas frecuentes» al final del artículo, con respuestas de 40–80 palabras. Marcar con FAQPage (valor semántico; no se espera rich result en Google).
A12: Schema.org | B12: BlogPosting (headline, description, datePublished, dateModified, author, publisher, mainEntityOfPage) + BreadcrumbList + FAQPage. Product/Offer no aplica dentro del blog.
... A24: Definición de «hecho» | B24: 1) Regla de redacción cumplida (sin cifras no respaldadas). 2) Title y meta dentro de los límites. 3) H1/H2 conforme al brief. 4) Enlaces internos ida y vuelta y enlaces a producto reales. 5) FAQ respondida. 6) PDF generado, revisado y cargado. 7) Schema válido. 8) Revisión en vista previa. 9) Estado actualizado en la hoja Backlog.

Sheet Claude Code
A1: Tema | B1: Instrucción
A2: Cómo usar este archivo | B2: Este Excel es la fuente de verdad del backlog del blog. Hojas: Backlog (estado y calendario), Briefs SEO (todo lo necesario para redactar), Guías PDF (entregables para Club 57), Especificaciones (reglas globales), Resumen (control).
A3: Siguiente artículo | B3: Tomar la fila de la hoja Backlog con menor fecha cuyo Estado sea «Backlog» o «Brief listo». Los 8 de Lanzamiento tienen la misma fecha: ejecutarlos en el orden de los IDs (B01 a B08). Al terminar el primer backlog se carga un segundo archivo con el mismo formato.
A4: Flujo por artículo | B4: 1) Leer la fila en Backlog, Briefs SEO y Guías PDF. 2) Leer la «Regla de redacción» de la fila y respetarla (no se investiga: se remite a etiqueta o ficha). 3) Revisar en el catálogo los productos a enlazar. 4) Redactar el artículo con la estructura del brief. 5) Crear la guía PDF. 6) Agregar enlaces internos ida y vuelta. 7) Validar title/meta/schema. 8) Dejar la pieza con su fecha de publicación programada. 9) Actualizar el Estado.
A5: Estados | B5: Backlog → Brief listo → Borrador → En revisión → Programado → Publicado (o Descartado). La lista desplegable de la columna Estado se puede cargar tal cual a la tabla de temas del módulo.
A6: Tabla de temas del módulo (siguiente ronda) | B6: La hoja Backlog puede sembrar una tabla (p. ej. blog_topics) con las columnas: ID, Etapa, Fecha, Clúster, Rol, Tipo, Título, Keyword, Intención, Audiencia, Estado, Guía PDF. El admin /blog solo marca el estado y consulta el backlog; no crea artículos.
A7: Aprobaciones pendientes antes de publicar | B7: Ninguna es obligatoria para empezar. Solo conviene que el cliente apruebe los 3 temas propuestos por Claude (B01, B02 y B10; columna Origen); si no responde, se publican igual porque no dependen de datos externos. Decisiones ya tomadas: no se nombra IPESA (B08) y «diablito» (B15) se trata solo como riesgo y solución segura.
A8: Prompt sugerido para iniciar | B8: «Lee el archivo backlog_blog_ferreteria57.xlsx. Ubica el siguiente artículo según la hoja Backlog (menor fecha con Estado Backlog o Brief listo). Sigue la hoja Especificaciones y el flujo de la hoja Claude Code. Respeta la «Regla de redacción» (sin investigar ni citar cifras no respaldadas), enlaza solo productos que existan en el catálogo, y muéstrame el borrador del artículo y de su guía PDF para revisión antes de programarlos.»

Sheet Notas
A1: Tema | B1: Nota
A2: Calendario | B2: Lanzamiento el viernes 9-oct-2026 con 8 artículos publicados el mismo día (fecha de referencia; se puede mover sin afectar el resto). Ritmo regular de 3 por semana en martes (fondo), jueves (corto) y sábado (fin de semana/proyecto DIY) del 13-oct-2026 al 30-ene-2027. La memoria del proyecto indica «3 por semana» pero no deja confirmados los días: martes, jueves y sábado es una propuesta a confirmar.
A3: Cobertura | B3: Cubre hasta el 31-ene-2027 (última fecha: sábado 30-ene). 58 temas: 56 programados y 2 en Reserva (jardín en primavera y comparativa de impermeabilizantes, para publicarse en feb–mar 2027, antes de la temporada de lluvias).
A4: Tope de 13 artículos al mes | B4: La cuota mensual incluye hasta 13 artículos con PDF al mes. Octubre tiene 9 (más los 8 de lanzamiento), noviembre 12, diciembre 14 y enero 13. Diciembre excede en 1: si se prefiere ajustarlo, mover B43 (jueves 31-dic) a Reserva. Confirmar si los 8 de lanzamiento forman parte del fee de integración.
A5: Temas agregados por Claude | B5: De las 55 ideas del cliente, todas están en el backlog. Se agregaron 3 piezas para cerrar huecos: B01 (guía de marcas Truper), B02 (kit básico de herramientas del hogar) y B10 (Club 57, conversión al registro). Están marcadas en la columna Origen y requieren aprobación del cliente.
A6: Orden y estacionalidad | B6: Los 8 de lanzamiento son pilares de cada clúster. Después se cuidó la estacionalidad: calentadores y boiler antes del frío (finales de octubre), soporte de TV antes de la temporada de ofertas de noviembre (sin citar fechas), seguridad y cajuela antes de vacaciones de diciembre, centro de carga en plena temporada de luces navideñas, y piezas ligeras el 24, 26 y 31 de diciembre.
A7: Keywords | B7: Son hipótesis sin volumen validado. Contrastar con Search Console y una herramienta de palabras clave antes de redactar. Se prefirieron keywords de intención clara y long-tail locales.
A8: Sin verificación previa | B8: Para no retrasar el lanzamiento, ningún tema depende de investigación o verificación: los artículos usan conocimiento general estable, no citan números de norma, estadísticas, fechas ni tarifas, y remiten al empaque, etiqueta o ficha para cualquier cifra técnica específica. Cada tema tiene su «Regla de redacción».
A9: Decisiones ya tomadas (no bloquean) | B9: 1) «Diablito» (B15): se trata solo como riesgo y solución segura, sin instrucciones de conexiones clandestinas. 2) IPESA (B08): no se nombra ninguna marca de pintura ajena al catálogo. 3) Marcas Truper (B01): se describen solo con lo que muestra el catálogo del sitio. 4) Artículos para dueños de ferreterías (B27 inventarios y B33 merchandising): se escriben con criterio general, sin datos internos de la tienda.
A10: Activos con potencial de enlaces | B10: El cálculo de pintura/impermeabilizante y la tabla de conversión mm/pulgadas podrían convertirse en calculadoras interactivas en el sitio. Requieren desarrollo adicional.
A11: Formato del Estado | B11: La columna Estado tiene lista desplegable: Backlog, Brief listo, Borrador, En revisión, Programado, Publicado, Descartado.
